Workbook

Sheet Summary
A1: Mary Grace Foods Inc.: 2025 vs 2026 Sources of Growth and the PHP 5B target
A2: All figures PHP millions, VAT-inclusive net sales. 2026 = actual to Oct 19 plus projection to Dec 31. Detail in the tabs; chart on SOG_Waterfall.
A4: Key number | B4: Value
A5: FY2025 actual | B5: =Model!B31 -> 4830.5303
A6: 2026 YTD actual (Jan 1-Oct 19) | B6: =Model!B25 -> 3859.9974
A7: 2026 YTD growth vs same days of 2025 | B7: =Model!B30 -> 0.040155013
A8: Needed in Oct 20-Dec 31 to reach target | B8: =Model!B26 -> 1140.0026
A9: Same days last year | B9: =Model!B27 -> 1119.5474
A10: Growth needed in the remainder (break-even) | B10: =Model!B28 -> 0.018270939
A11: Projected growth in the remainder (base case) | B11: =Model!B29 -> 0.033327252
A12: FY2026 projected total | B12: =Model!B23 -> 5016.8563
A13: Cushion / (gap) vs PHP 5B | B13: =Model!B24 -> 16.856257
A14: Share of YTD net growth from new stores | B14: =YTD_SOG!C16 -> 1.1430876
A15: Cafe same-store sales growth, YTD | B15: =YTD_SOG!B19 -> 0.016662447
A16: Kiosk same-store sales growth, YTD | B16: =YTD_SOG!B20 -> -0.037562595
A19: WHAT THE DATA SAYS
A20: 1. New stores, not same-store growth, drive the increase: new cafes and kiosks contribute more than 100% of YTD net growth. Closing stores take away roughly 40% of it. Same-store sales are up only a little in cafes and down in kiosks.
A21: 2. Cafe same-store growth is price-led. Beverages, All-Day Breakfast and Signature Cakes grew on higher average prices while units fell; Perfect Plates, Ensaymadas and Loaf Cakes shrank.
A22: 3. At the current run-rate and last year's Nov-Dec peak, 2026 lands at about PHP 5.02B: on target with only a thin cushion. The target needs roughly +1.8% over last year in the final 72 days; the base case assumes about +3.3%.
A23: 4. December carries about half of the remaining sales. A December that falls ~3% short of the projection (about flat on Dec 2025) would miss the target. Protect December first.
A24: 5. Extra headroom comes from many small levers (see Levers_Scenarios), not one big one: traffic, December cakes and Christmas kiosks, stabilising laggard categories, new-cafe ramp, delivery.
A25: 6. Item level (provisional until the full item pull): see Pareto_Items and Item_Priorities. About a fifth of items carry about 80% of the remaining revenue.
A26: Read Notes_Recon first: the Jan-Jun 2026 export hit the 1,000-row limit and was patched with estimates; re-running it will firm up the kiosk numbers.

Sheet SOG_Waterfall
A1: Sources of Growth waterfall: FY2025 baseline to FY2026 projected total (PHP millions)
A2: 2026 Total = actual Jan 1-Oct 19 + projected Oct 20-Dec 31 (see Model). Kiosk includes the single "Others" branch. Chart y-axis starts at 4,000 so the drivers are visible; read the data labels for true sizes.
A4: Bar | B4: Type | C4: Value (PHP M) | D4: Cumulative | E4: Base (hidden) | F4: Total / baseline | G4: Increase | H4: Decrease
A5: Cafe Baseline | B5: total | C5: =SUM(Model!C11:C14) -> 4302.2302 | D5: =IF(B5="total",C5,0+C5) -> 4302.2302 | E5: =IF(B5="total",0,MIN(0,D5)) -> 0 | F5: =IF(OR(B5="total",B5="float"),C5,0) -> 4302.2302 | G5: =IF(B5="delta",MAX(C5,0),0) -> 0 | H5: =IF(B5="delta",MAX(-C5,0),0) -> 0
A6: Kiosk Baseline | B6: float | C6: =SUM(Model!C15:C18) -> 528.30006 | D6: =IF(B6="total",C6,D5+C6) -> 4830.5303 | E6: =IF(B6="total",0,MIN(D5,D6)) -> 4302.2302 | F6: =IF(OR(B6="total",B6="float"),C6,0) -> 528.30006 | G6: =IF(B6="delta",MAX(C6,0),0) -> 0 | H6: =IF(B6="delta",MAX(-C6,0),0) -> 0
A7: Cafe Same-Store | B7: delta | C7: =Model!L11 -> 69.965897 | D7: =IF(B7="total",C7,D6+C7) -> 4900.4962 | E7: =IF(B7="total",0,MIN(D6,D7)) -> 4830.5303 | F7: =IF(OR(B7="total",B7="float"),C7,0) -> 0 | G7: =IF(B7="delta",MAX(C7,0),0) -> 69.965897 | H7: =IF(B7="delta",MAX(-C7,0),0) -> 0
A8: Cafe New 2025 | B8: delta | C8: =Model!L12 -> 146.39057 | D8: =IF(B8="total",C8,D7+C8) -> 5046.8867 | E8: =IF(B8="total",0,MIN(D7,D8)) -> 4900.4962 | F8: =IF(OR(B8="total",B8="float"),C8,0) -> 0 | G8: =IF(B8="delta",MAX(C8,0),0) -> 146.39057 | H8: =IF(B8="delta",MAX(-C8,0),0) -> 0
A9: Cafe New 2026 | B9: delta | C9: =Model!L13 -> 41.064835 | D9: =IF(B9="total",C9,D8+C9) -> 5087.9516 | E9: =IF(B9="total",0,MIN(D8,D9)) -> 5046.8867 | F9: =IF(OR(B9="total",B9="float"),C9,0) -> 0 | G9: =IF(B9="delta",MAX(C9,0),0) -> 41.064835 | H9: =IF(B9="delta",MAX(-C9,0),0) -> 0
A10: Cafe Closing | B10: delta | C10: =Model!L14 -> -47.165369 | D10: =IF(B10="total",C10,D9+C10) -> 5040.7862 | E10: =IF(B10="total",0,MIN(D9,D10)) -> 5040.7862 | F10: =IF(OR(B10="total",B10="float"),C10,0) -> 0 | G10: =IF(B10="delta",MAX(C10,0),0) -> 0 | H10: =IF(B10="delta",MAX(-C10,0),0) -> 47.165369
A11: Kiosk Same-Store | B11: delta | C11: =Model!L15 -> -13.939972 | D11: =IF(B11="total",C11,D10+C11) -> 5026.8462 | E11: =IF(B11="total",0,MIN(D10,D11)) -> 5026.8462 | F11: =IF(OR(B11="total",B11="float"),C11,0) -> 0 | G11: =IF(B11="delta",MAX(C11,0),0) -> 0 | H11: =IF(B11="delta",MAX(-C11,0),0) -> 13.939972
A12: Kiosk New | B12: delta | C12: =Model!L16+Model!L17 -> 11.097906 | D12: =IF(B12="total",C12,D11+C12) -> 5037.9441 | E12: =IF(B12="total",0,MIN(D11,D12)) -> 5026.8462 | F12: =IF(OR(B12="total",B12="float"),C12,0) -> 0 | G12: =IF(B12="delta",MAX(C12,0),0) -> 11.097906 | H12: =IF(B12="delta",MAX(-C12,0),0) -> 0
A13: Kiosk Closing | B13: delta | C13: =Model!L18 -> -21.087864 | D13: =IF(B13="total",C13,D12+C13) -> 5016.8563 | E13: =IF(B13="total",0,MIN(D12,D13)) -> 5016.8563 | F13: =IF(OR(B13="total",B13="float"),C13,0) -> 0 | G13: =IF(B13="delta",MAX(C13,0),0) -> 0 | H13: =IF(B13="delta",MAX(-C13,0),0) -> 21.087864
A14: 2026 Total | B14: total | C14: =D13 -> 5016.8563 | D14: =IF(B14="total",C14,D13+C14) -> 5016.8563 | E14: =IF(B14="total",0,MIN(D13,D14)) -> 0 | F14: =IF(OR(B14="total",B14="float"),C14,0) -> 5016.8563 | G14: =IF(B14="delta",MAX(C14,0),0) -> 0 | H14: =IF(B14="delta",MAX(-C14,0),0) -> 0
A15: PHP 5B Target | B15: total | C15: =Model!B3 -> 5000 | D15: =IF(B15="total",C15,D14+C15) -> 5000 | E15: =IF(B15="total",0,MIN(D14,D15)) -> 0 | F15: =IF(OR(B15="total",B15="float"),C15,0) -> 5000 | G15: =IF(B15="delta",MAX(C15,0),0) -> 0 | H15: =IF(B15="delta",MAX(-C15,0),0) -> 0
A17: Projected 2026 total vs target (PHP M) | C17: =C14-C15 -> 16.856257
A18: FY2025 total (Cafe + Kiosk baselines) | C18: =C5+C6 -> 4830.5303
A19: Net change FY26 vs FY25 | C19: =C14-C18 -> 186.326
A20: Check: drivers sum to net change (should be 0) | C20: =SUM(C7:C13)-C19 -> -7.3896445e-13

Sheet Monthly_Data
A1: Monthly net sales by segment (PHP millions, VAT-inclusive, reconciled to receipt-level net)
A2: Source: your SQL extracts (4 six-month runs). Each run is scaled so its total ties to the receipt-level header_net (see Notes_Recon). Oct 2026 = Oct 1-19 only. Jan-Jun 2026 Kiosk Same-Store and Others include ESTIMATED rows lost to the 1,000-row export limit.
A4: Group | B4: Store type | C4: Jan 2025 | D4: Feb 2025 | E4: Mar 2025 | F4: Apr 2025 | G4: May 2025 | H4: Jun 2025 | I4: Jul 2025 | J4: Aug 2025 | K4: Sep 2025 | L4: Oct 2025 | M4: Nov 2025 | N4: Dec 2025 | O4: Jan 2026 | P4: Feb 2026 | Q4: Mar 2026 | R4: Apr 2026 | S4: May 2026 | T4: Jun 2026 | U4: Jul 2026 | V4: Aug 2026 | W4: Sep 2026 | X4: Oct 2026
A5: Cafe | B5: Same-Store | C5: 335.63638 | D5: 314.48853 | E5: 324.76901 | F5: 288.72365 | G5: 341.29137 | H5: 324.41699 | I5: 306.66078 | J5: 337.44352 | K5: 295.22276 | L5: 324.73078 | M5: 323.8886 | N5: 448.19352 | O5: 333.88859 | P5: 320.66447 | Q5: 325.31037 | R5: 292.81107 | S5: 359.86815 | T5: 324.90355 | U5: 322.30923 | V5: 321.61511 | W5: 315.12581 | X5: 202.30027
A6: Cafe | B6: New 2025 | C6: 0 | D6: 0 | E6: 0 | F6: 2.7325774 | G6: 3.5982525 | H6: 3.1648482 | I6: 2.9187957 | J6: 10.413876 | K6: 9.616403 | L6: 10.410991 | M6: 11.419223 | N6: 21.716468 | O6: 20.240475 | P6: 17.844202 | Q6: 17.439732 | R6: 16.526036 | S6: 20.455033 | T6: 17.221276 | U6: 17.122504 | V6: 18.355271 | W6: 16.769727 | X6: 10.470947
A7: Cafe | B7: New 2026 | C7: 0 | D7: 0 | E7: 0 | F7: 0 | G7: 0 | H7: 0 | I7: 0 | J7: 0 | K7: 0 | L7: 0 | M7: 0 | N7: 0 | O7: 0 | P7: 2.1164445 | Q7: 2.5553541 | R7: 1.991209 | S7: 2.1679975 | T7: 3.1504039 | U7: 3.8389053 | V7: 3.2920752 | W7: 5.7543494 | X7: 3.8826328
A8: Cafe | B8: Closed | C8: 22.028422 | D8: 19.949403 | E8: 22.759012 | F8: 22.490717 | G8: 26.665522 | H8: 24.605881 | I8: 23.778537 | J8: 24.360195 | K8: 20.22845 | L8: 6.8727544 | M8: 22.213141 | N8: 24.820829 | O8: 22.305477 | P8: 18.338943 | Q8: 16.792232 | R8: 16.896546 | S8: 19.712982 | T8: 18.993498 | U8: 16.885955 | V8: 15.072557 | W8: 14.295504 | X8: 10.105414
A9: Kiosk & Others | B9: Same-Store | C9: 41.771286 | D9: 40.164388 | E9: 38.842717 | F9: 32.979325 | G9: 43.926367 | H9: 38.150931 | I9: 36.290218 | J9: 37.607887 | K9: 34.773233 | L9: 39.51781 | M9: 37.838286 | N9: 74.965065 | O9: 39.447539 | P9: 37.491763 | Q9: 36.134839 | R9: 31.253214 | S9: 41.915951 | T9: 37.022224 | U9: 35.938975 | V9: 36.013615 | W9: 36.642713 | X9: 23.015772
A10: Kiosk & Others | B10: New 2025 | C10: 0 | D10: 0 | E10: 0 | F10: 0 | G10: 0 | H10: 0 | I10: 0 | J10: 0 | K10: 0 | L10: 0 | M10: 0.01145355 | N10: 0.59181314 | O10: 0.32552057 | P10: 0.29949265 | Q10: 0.25383472 | R10: 0.24625941 | S10: 0.31598448 | T10: 0.31273332 | U10: 0.3180604 | V10: 0.27657921 | W10: 0.3344422 | X10: 0.21226174
A11: Kiosk & Others | B11: New 2026 | C11: 0 | D11: 0 | E11: 0 | F11: 0 | G11: 0 | H11: 0 | I11: 0 | J11: 0 | K11: 0 | L11: 0 | M11: 0 | N11: 0 | O11: 0 | P11: 0 | Q11: 0.22243152 | R11: 0.47111228 | S11: 0.68464643 | T11: 0.7016224 | U11: 0.64676837 | V11: 0.72152757 | W11: 0.86973692 | X11: 0.75479935
A12: Kiosk & Others | B12: Closed | C12: 2.8599771 | D12: 2.8162003 | E12: 2.734565 | F12: 2.5049782 | G12: 2.9899372 | H12: 2.7544732 | I12: 2.5299199 | J12: 2.6559581 | K12: 1.6852871 | L12: 1.858194 | M12: 1.8031961 | N12: 3.6765971 | O12: 1.8810517 | P12: 1.1321888 | Q12: 0.76058333 | R12: 0.68664193 | S12: 0.66457038 | T12: 0.56320221 | U12: 0.58208878 | V12: 0.57754717 | W12: 0.55292735 | X12: 0.36186733
A13: Total | C13: =SUM(C5:C12) -> 402.29606 | D13: =SUM(D5:D12) -> 377.41853 | E13: =SUM(E5:E12) -> 389.10531 | F13: =SUM(F5:F12) -> 349.43124 | G13: =SUM(G5:G12) -> 418.47144 | H13: =SUM(H5:H12) -> 393.09312 | I13: =SUM(I5:I12) -> 372.17825 | J13: =SUM(J5:J12) -> 412.48144 | ... X13: =SUM(X5:X12) -> 251.10397
A15: YoY growth, total company | O15: =O13/C13-1 -> 0.039256133 | P15: =P13/D13-1 -> 0.054234173 | Q15: =Q13/E13-1 -> 0.026635636 | R15: =R13/F13-1 -> 0.032769938 | S15: =S13/G13-1 -> 0.065270562 | T15: =T13/H13-1 -> 0.024867864 | U15: =U13/I13-1 -> 0.068419459 | V15: =V13/J13-1 -> -0.040140362 | W15: =W13/K13-1 -> 0.079715056 | X15: =X13/(L13*Model!$B$4/Model!$B$5)-1 -> 0.068612602
A16: Oct 2026 growth compares Oct 1-19, 2026 with 19/31 of Oct 2025 (assumes an even daily pace).

Sheet Model
A1: Projection engine: 2026 landing vs the PHP 5B target (PHP millions)
A3: FY2026 target (PHP M) | B3: 5000 | C3: User-stated: target is for full-year 2026, VAT-inclusive
A4: Days of Oct 2026 in data (Oct 1-19) | B4: 19 | C4: Edit if you refresh the data to a later date
A5: Days in October | B5: 31
A6: Days of Oct still to come (Oct 20-31) | B6: =B5-B4 -> 12
A9: Group | B9: Store type | C9: FY2025 actual | D9: 2025 YTD (Jan 1-Oct 19) | E9: 2026 YTD actual | F9: 2025 remainder (Oct 20-Dec 31) | G9: Q3'25 avg / month | H9: Q3'26 avg / month | I9: Seasonal index (remainder / Q3 month) | J9: 2026 remainder (projected) | K9: FY2026 projected | L9: Change FY26 vs FY25 | M9: Change YTD (like-for-like) | N9: YTD growth %
A11: Cafe | B11: Same-Store | C11: =SUM(Monthly_Data!C5:N5) -> 3965.4659 | D11: =SUM(Monthly_Data!C5:K5)+Monthly_Data!L5*$B$4/$B$5 -> 3067.6815 | E11: =SUM(Monthly_Data!O5:W5)+Monthly_Data!X5 -> 3118.7966 | F11: =Monthly_Data!L5*$B$6/$B$5+Monthly_Data!M5+Monthly_Data!N5 -> 897.78436 | G11: =AVERAGE(Monthly_Data!I5:K5) -> 313.10902 | H11: =AVERAGE(Monthly_Data!U5:W5) -> 319.68339 | I11: =$F$11/$G$11 -> 2.8673219 | J11: =H11*I11 -> 916.63517 | K11: =E11+J11 -> 4035.4318 | L11: =K11-C11 -> 69.965897 | M11: =E11-D11 -> 51.115082 | N11: =IF(D11=0,"n/a",E11/D11-1) -> 0.016662447
A12: Cafe | B12: New 2025 | C12: =SUM(Monthly_Data!C6:N6) -> 75.991435 | D12: =SUM(Monthly_Data!C6:K6)+Monthly_Data!L6*$B$4/$B$5 -> 38.825682 | E12: =SUM(Monthly_Data!O6:W6)+Monthly_Data!X6 -> 172.4452 | F12: =Monthly_Data!L6*$B$6/$B$5+Monthly_Data!M6+Monthly_Data!N6 -> 37.165753 | G12: =AVERAGE(Monthly_Data!I6:K6) -> 7.6496914 | H12: =AVERAGE(Monthly_Data!U6:W6) -> 17.415834 | I12: =$F$11/$G$11 -> 2.8673219 | J12: =H12*I12 -> 49.936802 | K12: =E12+J12 -> 222.382 | L12: =K12-C12 -> 146.39057 | M12: =E12-D12 -> 133.61952 | N12: =IF(D12=0,"n/a",E12/D12-1) -> 3.4415241
A13: Cafe | B13: New 2026 | C13: =SUM(Monthly_Data!C7:N7) -> 0 | D13: =SUM(Monthly_Data!C7:K7)+Monthly_Data!L7*$B$4/$B$5 -> 0 | E13: =SUM(Monthly_Data!O7:W7)+Monthly_Data!X7 -> 28.749372 | F13: =Monthly_Data!L7*$B$6/$B$5+Monthly_Data!M7+Monthly_Data!N7 -> 0 | G13: =AVERAGE(Monthly_Data!I7:K7) -> 0 | H13: =AVERAGE(Monthly_Data!U7:W7) -> 4.29511 | I13: =$F$11/$G$11 -> 2.8673219 | J13: =H13*I13 -> 12.315463 | K13: =E13+J13 -> 41.064835 | L13: =K13-C13 -> 41.064835 | M13: =E13-D13 -> 28.749372 | N13: =IF(D13=0,"n/a",E13/D13-1) -> n/a
A14: Cafe | B14: Closed | C14: =SUM(Monthly_Data!C8:N8) -> 260.77286 | D14: =SUM(Monthly_Data!C8:K8)+Monthly_Data!L8*$B$4/$B$5 -> 211.07847 | E14: =SUM(Monthly_Data!O8:W8)+Monthly_Data!X8 -> 169.39911 | F14: =Monthly_Data!L8*$B$6/$B$5+Monthly_Data!M8+Monthly_Data!N8 -> 49.69439 | G14: =AVERAGE(Monthly_Data!I8:K8) -> 22.789061 | H14: =AVERAGE(Monthly_Data!U8:W8) -> 15.418005 | I14: =$F$11/$G$11 -> 2.8673219 | J14: =H14*I14 -> 44.208384 | K14: =E14+J14 -> 213.60749 | L14: =K14-C14 -> -47.165369 | M14: =E14-D14 -> -41.679363 | N14: =IF(D14=0,"n/a",E14/D14-1) -> -0.19745909
A15: Kiosk & Others | B15: Same-Store | C15: =SUM(Monthly_Data!C9:N9) -> 496.82751 | D15: =SUM(Monthly_Data!C9:K9)+Monthly_Data!L9*$B$4/$B$5 -> 368.72694 | E15: =SUM(Monthly_Data!O9:W9)+Monthly_Data!X9 -> 354.8766 | F15: =Monthly_Data!L9*$B$6/$B$5+Monthly_Data!M9+Monthly_Data!N9 -> 128.10057 | G15: =AVERAGE(Monthly_Data!I9:K9) -> 36.223779 | H15: =AVERAGE(Monthly_Data!U9:W9) -> 36.198434 | I15: =$F$15/$G$15 -> 3.5363667 | J15: =H15*I15 -> 128.01094 | K15: =E15+J15 -> 482.88754 | L15: =K15-C15 -> -13.939972 | M15: =E15-D15 -> -13.850341 | N15: =IF(D15=0,"n/a",E15/D15-1) -> -0.037562595
A16: Kiosk & Others | B16: New 2025 | C16: =SUM(Monthly_Data!C10:N10) -> 0.60326669 | D16: =SUM(Monthly_Data!C10:K10)+Monthly_Data!L10*$B$4/$B$5 -> 0 | E16: =SUM(Monthly_Data!O10:W10)+Monthly_Data!X10 -> 2.8951687 | F16: =Monthly_Data!L10*$B$6/$B$5+Monthly_Data!M10+Monthly_Data!N10 -> 0.60326669 | G16: =AVERAGE(Monthly_Data!I10:K10) -> 0 | H16: =AVERAGE(Monthly_Data!U10:W10) -> 0.30969394 | I16: =$F$15/$G$15 -> 3.5363667 | J16: =H16*I16 -> 1.0951913 | K16: =E16+J16 -> 3.99036 | L16: =K16-C16 -> 3.3870933 | M16: =E16-D16 -> 2.8951687 | N16: =IF(D16=0,"n/a",E16/D16-1) -> n/a
A17: Kiosk & Others | B17: New 2026 | C17: =SUM(Monthly_Data!C11:N11) -> 0 | D17: =SUM(Monthly_Data!C11:K11)+Monthly_Data!L11*$B$4/$B$5 -> 0 | E17: =SUM(Monthly_Data!O11:W11)+Monthly_Data!X11 -> 5.0726448 | F17: =Monthly_Data!L11*$B$6/$B$5+Monthly_Data!M11+Monthly_Data!N11 -> 0 | G17: =AVERAGE(Monthly_Data!I11:K11) -> 0 | H17: =AVERAGE(Monthly_Data!U11:W11) -> 0.74601095 | I17: =$F$15/$G$15 -> 3.5363667 | J17: =H17*I17 -> 2.6381683 | K17: =E17+J17 -> 7.7108131 | L17: =K17-C17 -> 7.7108131 | M17: =E17-D17 -> 5.0726448 | N17: =IF(D17=0,"n/a",E17/D17-1) -> n/a
A18: Kiosk & Others | B18: Closed | C18: =SUM(Monthly_Data!C12:N12) -> 30.869283 | D18: =SUM(Monthly_Data!C12:K12)+Monthly_Data!L12*$B$4/$B$5 -> 24.670189 | E18: =SUM(Monthly_Data!O12:W12)+Monthly_Data!X12 -> 7.7626689 | F18: =Monthly_Data!L12*$B$6/$B$5+Monthly_Data!M12+Monthly_Data!N12 -> 6.1990941 | G18: =AVERAGE(Monthly_Data!I12:K12) -> 2.2903884 | H18: =AVERAGE(Monthly_Data!U12:W12) -> 0.57085443 | I18: =$F$15/$G$15 -> 3.5363667 | J18: =H18*I18 -> 2.0187506 | K18: =E18+J18 -> 9.7814195 | L18: =K18-C18 -> -21.087864 | M18: =E18-D18 -> -16.90752 | N18: =IF(D18=0,"n/a",E18/D18-1) -> -0.68534214
A19: Total | C19: =SUM(C11:C18) -> 4830.5303 | D19: =SUM(D11:D18) -> 3710.9828 | E19: =SUM(E11:E18) -> 3859.9974 | F19: =SUM(F11:F18) -> 1119.5474 | J19: =SUM(J11:J18) -> 1156.8589 | K19: =SUM(K11:K18) -> 5016.8563 | L19: =SUM(L11:L18) -> 186.326 | M19: =SUM(M11:M18) -> 149.01456 | N19: =E19/D19-1 -> 0.040155013
A20: Method: remainder = Q3-2026 monthly run-rate x seasonal index. The index is each channel's Same-Store (Oct 20-Dec 31, 2025) divided by its 2025 Q3 monthly average, i.e. it carries last year's Nov-Dec peak. One year of seasonality only (2024 not extracted).
A22: Headline numbers
A23: FY2026 projected total | B23: =K19 -> 5016.8563
A24: Projected cushion / (gap) vs target | B24: =K19-B3 -> 16.856257
A25: 2026 YTD actual (Jan 1-Oct 19) | B25: =E19 -> 3859.9974
A26: Needed in Oct 20-Dec 31 to hit target | B26: =B3-E19 -> 1140.0026
A27: Same days last year (2025 remainder) | B27: =F19 -> 1119.5474
A28: Required YoY growth in the remainder | B28: =B26/B27-1 -> 0.018270939
A29: Projected YoY growth in the remainder | B29: =J19/F19-1 -> 0.033327252
A30: YTD YoY growth (like-for-like) | B30: =E19/D19-1 -> 0.040155013
A31: FY2025 actual | B31: =C19 -> 4830.5303
A32: FY2026 vs FY2025 growth | B32: =K19/C19-1 -> 0.038572578

Sheet YTD_SOG
A1: Like-for-like YTD sources of growth: Jan 1-Oct 19, 2026 vs same days of 2025 (PHP millions)
A3: Source | B3: 2025 YTD | C3: 2026 YTD | D3: Change | E3: Growth % | F3: Share of net growth
A4: Cafe Same-Store | B4: =Model!D11 -> 3067.6815 | C4: =Model!E11 -> 3118.7966 | D4: =C4-B4 -> 51.115082 | E4: =IF(B4=0,"new",C4/B4-1) -> 0.016662447 | F4: =D4/$D$11 -> 0.34302071
A5: Kiosk Same-Store (incl. Others) | B5: =Model!D15 -> 368.72694 | C5: =Model!E15 -> 354.8766 | D5: =C5-B5 -> -13.850341 | E5: =IF(B5=0,"new",C5/B5-1) -> -0.037562595 | F5: =D5/$D$11 -> -0.092946223
A6: New cafes opened 2025 | B6: =Model!D12 -> 38.825682 | C6: =Model!E12 -> 172.4452 | D6: =C6-B6 -> 133.61952 | E6: =IF(B6=0,"new",C6/B6-1) -> 3.4415241 | F6: =D6/$D$11 -> 0.89668766
A7: New cafes opened 2026 | B7: =Model!D13 -> 0 | C7: =Model!E13 -> 28.749372 | D7: =C7-B7 -> 28.749372 | E7: =IF(B7=0,"new",C7/B7-1) -> new | F7: =D7/$D$11 -> 0.19292995
A8: New kiosks (2025 + 2026) | B8: =Model!D16+Model!D17 -> 0 | C8: =Model!E16+Model!E17 -> 7.9678135 | D8: =C8-B8 -> 7.9678135 | E8: =IF(B8=0,"new",C8/B8-1) -> new | F8: =D8/$D$11 -> 0.053470032
A9: Closing cafes | B9: =Model!D14 -> 211.07847 | C9: =Model!E14 -> 169.39911 | D9: =C9-B9 -> -41.679363 | E9: =IF(B9=0,"new",C9/B9-1) -> -0.19745909 | F9: =D9/$D$11 -> -0.27969993
A10: Closing kiosks | B10: =Model!D18 -> 24.670189 | C10: =Model!E18 -> 7.7626689 | D10: =C10-B10 -> -16.90752 | E10: =IF(B10=0,"new",C10/B10-1) -> -0.68534214 | F10: =D10/$D$11 -> -0.1134622
A11: Total company | B11: =SUM(B4:B10) -> 3710.9828 | C11: =SUM(C4:C10) -> 3859.9974 | D11: =SUM(D4:D10) -> 149.01456 | E11: =C11/B11-1 -> 0.040155013 | F11: =SUM(F4:F10) -> 1
A13: Roll-up
A14: Group | B14: Change (PHP M) | C14: Share of net growth | D14: 2025 base | E14: Growth on own base
A15: Same-store (Cafe + Kiosk) | B15: =D4+D5 -> 37.264741 | C15: =B15/$D$11 -> 0.25007449 | D15: =B4+B5 -> 3436.4085 | E15: =IF(D15=0,"n/a",B15/D15) -> 0.010844095
A16: New stores (all cohorts) | B16: =D6+D7+D8 -> 170.33671 | C16: =B16/$D$11 -> 1.1430876 | D16: =B6+B7+B8 -> 38.825682 | E16: =IF(D16=0,"n/a",B16/D16) -> 4.3872173
A17: Closing stores | B17: =D9+D10 -> -58.586884 | C17: =B17/$D$11 -> -0.39316213 | D17: =B9+B10 -> 235.74866 | E17: =IF(D17=0,"n/a",B17/D17) -> -0.24851417
A19: Same-store sales growth (SSSG): Cafe | B19: =E4 -> 0.016662447
A20: Same-store sales growth (SSSG): Kiosk | B20: =E5 -> -0.037562595
A21: Same-store sales growth (SSSG): Cafe + Kiosk combined | B21: =(C4+C5)/(B4+B5)-1 -> 0.010844095
A23: Note: "Closing" = branches with a date_closed in the branches table; they still trade for part of the period. Same-Store = opened before 2025 with no close date.

Sheet P-Mix
A1: Product mix analysis: YTD 2026 vs same days of 2025 (PHP millions, net sales)
A2: Values are YTD (Jan 1-Oct 19; Oct 2025 pro-rated 19/31). Mix shift in percentage points. Price = net sales per unit, so a price change also reflects pack/size/discount mix. Kiosk H1-2026 lines marked * are partly estimated.
A4: A. CAFE - SAME-STORES ONLY (cleanest read of the menu)
A5: Category | B5: 2025 YTD | C5: 2026 YTD | D5: Change | E5: Growth % | F5: Mix 2025 | G5: Mix 2026 | H5: Mix shift (pp) | I5: Contribution to channel growth (pp) | J5: Qty 2025 | K5: Qty 2026 | L5: Qty growth % | M5: Avg price growth %
A6: ALL-DAY BREAKFAST | B6: 553.10898 | C6: 564.49609 | D6: =C6-B6 -> 11.387117 | E6: =IF(B6<0.05,"new",C6/B6-1) -> 0.020587474 | F6: =B6/B$30 -> 0.18030195 | G6: =C6/C$30 -> 0.18099805 | H6: =(G6-F6)*100 -> 0.069609139 | I6: =D6/B$30*100 -> 0.37119618 | J6: 1829091.3 | K6: 1823507 | L6: =IF(J6<1,"new",K6/J6-1) -> -0.0030530584 | M6: =IF(OR(J6<1,K6<1,B6<=0),"n/a",(C6/K6)/(B6/J6)-1) -> 0.023712929
A7: SIGNATURE CAKES | B7: 503.83325 | C7: 508.6621 | D7: =C7-B7 -> 4.8288447 | E7: =IF(B7<0.05,"new",C7/B7-1) -> 0.009584212 | F7: =B7/B$30 -> 0.1642391 | G7: =C7/C$30 -> 0.16309563 | H7: =(G7-F7)*100 -> -0.114347 | I7: =D7/B$30*100 -> 0.15741023 | J7: 915229.84 | K7: 900082 | L7: =IF(J7<1,"new",K7/J7-1) -> -0.016550858 | M7: =IF(OR(J7<1,K7<1,B7<=0),"n/a",(C7/K7)/(B7/J7)-1) -> 0.026574907
A8: FLAVORFUL PASTAS | B8: 479.34181 | C8: 480.20315 | D8: =C8-B8 -> 0.86134656 | E8: =IF(B8<0.05,"new",C8/B8-1) -> 0.001796936 | F8: =B8/B$30 -> 0.1562554 | G8: =C8/C$30 -> 0.15397065 | H8: =(G8-F8)*100 -> -0.22847469 | I8: =D8/B$30*100 -> 0.028078096 | J8: 970338.84 | K8: 956500 | L8: =IF(J8<1,"new",K8/J8-1) -> -0.014261862 | M8: =IF(OR(J8<1,K8<1,B8<=0),"n/a",(C8/K8)/(B8/J8)-1) -> 0.01629114
A9: BEVERAGES | B9: 359.55043 | C9: 376.12938 | D9: =C9-B9 -> 16.578952 | E9: =IF(B9<0.05,"new",C9/B9-1) -> 0.046110228 | F9: =B9/B$30 -> 0.11720592 | G9: =C9/C$30 -> 0.1206008 | H9: =(G9-F9)*100 -> 0.33948869 | I9: =D9/B$30*100 -> 0.54043915 | J9: 3230801.7 | K9: 3065291 | L9: =IF(J9<1,"new",K9/J9-1) -> -0.051228981 | M9: =IF(OR(J9<1,K9<1,B9<=0),"n/a",(C9/K9)/(B9/J9)-1) -> 0.10259505
A10: CHEESE ROLLS | B10: 235.16169 | C10: 239.9889 | D10: =C10-B10 -> 4.8272028 | E10: =IF(B10<0.05,"new",C10/B10-1) -> 0.020527165 | F10: =B10/B$30 -> 0.076657792 | G10: =C10/C$30 -> 0.076949197 | H10: =(G10-F10)*100 -> 0.029140517 | I10: =D10/B$30*100 -> 0.15735671 | J10: 767047.65 | K10: 781279 | L10: =IF(J10<1,"new",K10/J10-1) -> 0.018553417 | M10: =IF(OR(J10<1,K10<1,B10<=0),"n/a",(C10/K10)/(B10/J10)-1) -> 0.0019377948
A11: ENSAYMADAS | B11: 175.90865 | C11: 166.13618 | D11: =C11-B11 -> -9.7724777 | E11: =IF(B11<0.05,"new",C11/B11-1) -> -0.055554275 | F11: =B11/B$30 -> 0.057342541 | G11: =C11/C$30 -> 0.053269321 | H11: =(G11-F11)*100 -> -0.40732205 | I11: =D11/B$30*100 -> -0.31856233 | J11: 745705.94 | K11: 694514 | L11: =IF(J11<1,"new",K11/J11-1) -> -0.068648958 | M11: =IF(OR(J11<1,K11<1,B11<=0),"n/a",(C11/K11)/(B11/J11)-1) -> 0.01405988
A12: FRESH SALADS | B12: 126.95191 | C12: 126.15338 | D12: =C12-B12 -> -0.79853062 | E12: =IF(B12<0.05,"new",C12/B12-1) -> -0.0062900246 | F12: =B12/B$30 -> 0.041383665 | G12: =C12/C$30 -> 0.040449375 | H12: =(G12-F12)*100 -> -0.093428986 | I12: =D12/B$30*100 -> -0.026030427 | J12: 240373.52 | K12: 247827 | L12: =IF(J12<1,"new",K12/J12-1) -> 0.031007925 | M12: =IF(OR(J12<1,K12<1,B12<=0),"n/a",(C12/K12)/(B12/J12)-1) -> -0.0361762
A13: PERFECT PLATES | B13: 132.14967 | C13: 121.39871 | D13: =C13-B13 -> -10.750956 | E13: =IF(B13<0.05,"new",C13/B13-1) -> -0.081354396 | F13: =B13/B$30 -> 0.043078027 | G13: =C13/C$30 -> 0.038924857 | H13: =(G13-F13)*100 -> -0.41531702 | I13: =D13/B$30*100 -> -0.35045869 | J13: 526717.61 | K13: 491316 | L13: =IF(J13<1,"new",K13/J13-1) -> -0.067211751 | M13: =IF(OR(J13<1,K13<1,B13<=0),"n/a",(C13/K13)/(B13/J13)-1) -> -0.015161689
A14: MAINS | B14: 91.276517 | C14: 95.540565 | D14: =C14-B14 -> 4.2640485 | E14: =IF(B14<0.05,"new",C14/B14-1) -> 0.046715724 | F14: =B14/B$30 -> 0.029754235 | G14: =C14/C$30 -> 0.030633791 | H14: =(G14-F14)*100 -> 0.087955668 | I14: =D14/B$30*100 -> 0.13899906 | J14: 115442.29 | K14: 128084 | L14: =IF(J14<1,"new",K14/J14-1) -> 0.10950675 | M14: =IF(OR(J14<1,K14<1,B14<=0),"n/a",(C14/K14)/(B14/J14)-1) -> -0.056593638
A15: SOUPS | B15: 72.373939 | C15: 76.044511 | D15: =C15-B15 -> 3.6705716 | E15: =IF(B15<0.05,"new",C15/B15-1) -> 0.050716759 | F15: =B15/B$30 -> 0.02359239 | G15: =C15/C$30 -> 0.024382645 | H15: =(G15-F15)*100 -> 0.079025501 | I15: =D15/B$30*100 -> 0.11965296 | J15: 284827.39 | K15: 319411 | L15: =IF(J15<1,"new",K15/J15-1) -> 0.12141955 | M15: =IF(OR(J15<1,K15<1,B15<=0),"n/a",(C15/K15)/(B15/J15)-1) -> -0.063047581
A16: PIZZAS | B16: 68.306831 | C16: 69.38341 | D16: =C16-B16 -> 1.0765786 | E16: =IF(B16<0.05,"new",C16/B16-1) -> 0.015760921 | F16: =B16/B$30 -> 0.022266598 | G16: =C16/C$30 -> 0.022246853 | H16: =(G16-F16)*100 -> -0.001974492 | I16: =D16/B$30*100 -> 0.035094209 | J16: 104096.45 | K16: 104671 | L16: =IF(J16<1,"new",K16/J16-1) -> 0.0055193849 | M16: =IF(OR(J16<1,K16<1,B16<=0),"n/a",(C16/K16)/(B16/J16)-1) -> 0.01018532
A17: HEARTY SANDWICHES | B17: 63.307481 | C17: 69.269633 | D17: =C17-B17 -> 5.9621517 | E17: =IF(B17<0.05,"new",C17/B17-1) -> 0.09417768 | F17: =B17/B$30 -> 0.020636914 | G17: =C17/C$30 -> 0.022210372 | H17: =(G17-F17)*100 -> 0.15734576 | I17: =D17/B$30*100 -> 0.19435367 | J17: 146526.81 | K17: 147564 | L17: =IF(J17<1,"new",K17/J17-1) -> 0.0070785242 | M17: =IF(OR(J17<1,K17<1,B17<=0),"n/a",(C17/K17)/(B17/J17)-1) -> 0.086486956
... A29: Other small categories (<PHP 0.3M) | B29: 0.040320673 | C29: 0.25853454 | D29: =C29-B29 -> 0.21821386 | E29: =IF(B29<0.05,"new",C29/B29-1) -> new | F29: =B29/B$30 -> 1.3143696e-05 | G29: =C29/C$30 -> 8.2895606e-05 | H29: =(G29-F29)*100 -> 0.006975191 | I29: =D29/B$30*100 -> 0.0071133154 | J29: 20048.419 | K29: 11282 | L29: =IF(J29<1,"new",K29/J29-1) -> -0.43726237 | M29: =IF(OR(J29<1,K29<1,B29<=0),"n/a",(C29/K29)/(B29/J29)-1) -> 10.394226
A30: Total | B30: =SUM(B6:B29) -> 3067.6815 | C30: =SUM(C6:C29) -> 3118.7966 | D30: =SUM(D6:D29) -> 51.115082 | E30: =C30/B30-1 -> 0.016662447 | I30: =SUM(I6:I29) -> 1.6662447 | J30: =SUM(J6:J29) -> 14014022 | K30: =SUM(K6:K29) -> 13912236 | L30: =K30/J30-1 -> -0.007263122 | M30: =(C30/K30)/(B30/J30)-1 -> 0.024100615
A33: B. CAFE - ALL STORES (includes new / closing stores)
A34: Category | B34: 2025 YTD | C34: 2026 YTD | D34: Change | E34: Growth % | F34: Mix 2025 | G34: Mix 2026 | H34: Mix shift (pp) | I34: Contribution to channel growth (pp) | J34: Qty 2025 | K34: Qty 2026 | L34: Qty growth % | M34: Avg price growth %
A35: ALL-DAY BREAKFAST | B35: 606.97252 | C35: 642.02016 | D35: =C35-B35 -> 35.047643 | E35: =IF(B35<0.05,"new",C35/B35-1) -> 0.05774173 | F35: =B35/B$60 -> 0.18295609 | G35: =C35/C$60 -> 0.18399207 | H35: =(G35-F35)*100 -> 0.10359812 | I35: =D35/B$60*100 -> 1.0564201 | J35: 1991147.3 | K35: 2056321 | L35: =IF(J35<1,"new",K35/J35-1) -> 0.03273172 | M35: =IF(OR(J35<1,K35<1,B35<=0),"n/a",(C35/K35)/(B35/J35)-1) -> 0.024217335
A36: SIGNATURE CAKES | B36: 524.9813 | C36: 555.92469 | D36: =C36-B36 -> 30.943399 | E36: =IF(B36<0.05,"new",C36/B36-1) -> 0.058941907 | F36: =B36/B$60 -> 0.15824197 | G36: =C36/C$60 -> 0.15931858 | H36: =(G36-F36)*100 -> 0.1076606 | I36: =D36/B$60*100 -> 0.93270835 | J36: 967070.65 | K36: 987959 | L36: =IF(J36<1,"new",K36/J36-1) -> 0.021599616 | M36: =IF(OR(J36<1,K36<1,B36<=0),"n/a",(C36/K36)/(B36/J36)-1) -> 0.036552765
A37: FLAVORFUL PASTAS | B37: 517.6485 | C37: 532.53217 | D37: =C37-B37 -> 14.883674 | E37: =IF(B37<0.05,"new",C37/B37-1) -> 0.028752473 | F37: =B37/B$60 -> 0.15603169 | G37: =C37/C$60 -> 0.15261468 | H37: =(G37-F37)*100 -> -0.34170122 | I37: =D37/B$60*100 -> 0.44862969 | J37: 1043808.2 | K37: 1056742 | L37: =IF(J37<1,"new",K37/J37-1) -> 0.012390949 | M37: =IF(OR(J37<1,K37<1,B37<=0),"n/a",(C37/K37)/(B37/J37)-1) -> 0.016161271
A38: BEVERAGES | B38: 395.09345 | C38: 422.09393 | D38: =C38-B38 -> 27.000475 | E38: =IF(B38<0.05,"new",C38/B38-1) -> 0.068339465 | F38: =B38/B$60 -> 0.11909065 | G38: =C38/C$60 -> 0.12096495 | H38: =(G38-F38)*100 -> 0.18742963 | I38: =D38/B$60*100 -> 0.81385916 | J38: 3512210.7 | K38: 3413253 | L38: =IF(J38<1,"new",K38/J38-1) -> -0.028175343 | M38: =IF(OR(J38<1,K38<1,B38<=0),"n/a",(C38/K38)/(B38/J38)-1) -> 0.099312985
A39: CHEESE ROLLS | B39: 265.36903 | C39: 277.62597 | D39: =C39-B39 -> 12.256936 | E39: =IF(B39<0.05,"new",C39/B39-1) -> 0.04618827 | F39: =B39/B$60 -> 0.079988598 | G39: =C39/C$60 -> 0.079562887 | H39: =(G39-F39)*100 -> -0.042571154 | I39: =D39/B$60*100 -> 0.3694535 | J39: 844938.74 | K39: 882157 | L39: =IF(J39<1,"new",K39/J39-1) -> 0.044048469 | M39: =IF(OR(J39<1,K39<1,B39<=0),"n/a",(C39/K39)/(B39/J39)-1) -> 0.0020495224
A40: ENSAYMADAS | B40: 195.88264 | C40: 190.245 | D40: =C40-B40 -> -5.6376392 | E40: =IF(B40<0.05,"new",C40/B40-1) -> -0.028780699 | F40: =B40/B$60 -> 0.059043731 | G40: =C40/C$60 -> 0.054520985 | H40: =(G40-F40)*100 -> -0.45227455 | I40: =D40/B$60*100 -> -0.16993198 | J40: 810415.39 | K40: 781066 | L40: =IF(J40<1,"new",K40/J40-1) -> -0.036215239 | M40: =IF(OR(J40<1,K40<1,B40<=0),"n/a",(C40/K40)/(B40/J40)-1) -> 0.0077139012
A41: FRESH SALADS | B41: 136.18202 | C41: 139.55375 | D41: =C41-B41 -> 3.3717252 | E41: =IF(B41<0.05,"new",C41/B41-1) -> 0.02475896 | F41: =B41/B$60 -> 0.041048532 | G41: =C41/C$60 -> 0.039993734 | H41: =(G41-F41)*100 -> -0.1054798 | I41: =D41/B$60*100 -> 0.1016319 | J41: 260356.9 | K41: 278120 | L41: =IF(J41<1,"new",K41/J41-1) -> 0.068225949 | M41: =IF(OR(J41<1,K41<1,B41<=0),"n/a",(C41/K41)/(B41/J41)-1) -> -0.040690819
A42: PERFECT PLATES | B42: 141.56355 | C42: 134.24496 | D42: =C42-B42 -> -7.3185866 | E42: =IF(B42<0.05,"new",C42/B42-1) -> -0.051698241 | F42: =B42/B$60 -> 0.042670654 | G42: =C42/C$60 -> 0.038472327 | H42: =(G42-F42)*100 -> -0.41983271 | I42: =D42/B$60*100 -> -0.22059978 | J42: 563281.29 | K42: 542139 | L42: =IF(J42<1,"new",K42/J42-1) -> -0.03753416 | M42: =IF(OR(J42<1,K42<1,B42<=0),"n/a",(C42/K42)/(B42/J42)-1) -> -0.01471645
A43: MAINS | B43: 94.681008 | C43: 107.34281 | D43: =C43-B43 -> 12.661802 | E43: =IF(B43<0.05,"new",C43/B43-1) -> 0.13373117 | F43: =B43/B$60 -> 0.02853913 | G43: =C43/C$60 -> 0.030762626 | H43: =(G43-F43)*100 -> 0.22234967 | I43: =D43/B$60*100 -> 0.38165712 | J43: 119687.58 | K43: 143186 | L43: =IF(J43<1,"new",K43/J43-1) -> 0.19633131 | M43: =IF(OR(J43<1,K43<1,B43<=0),"n/a",(C43/K43)/(B43/J43)-1) -> -0.052326759
A44: SOUPS | B44: 77.115731 | C44: 84.016696 | D44: =C44-B44 -> 6.9009647 | E44: =IF(B44<0.05,"new",C44/B44-1) -> 0.089488416 | F44: =B44/B$60 -> 0.023244533 | G44: =C44/C$60 -> 0.024077758 | H44: =(G44-F44)*100 -> 0.083322483 | I44: =D44/B$60*100 -> 0.20801165 | J44: 302465.55 | K44: 351836 | L44: =IF(J44<1,"new",K44/J44-1) -> 0.16322669 | M44: =IF(OR(J44<1,K44<1,B44<=0),"n/a",(C44/K44)/(B44/J44)-1) -> -0.06339115
A45: HEARTY SANDWICHES | B45: 69.124431 | C45: 77.223335 | D45: =C45-B45 -> 8.0989046 | E45: =IF(B45<0.05,"new",C45/B45-1) -> 0.11716414 | F45: =B45/B$60 -> 0.020835763 | G45: =C45/C$60 -> 0.022130896 | H45: =(G45-F45)*100 -> 0.1295133 | I45: =D45/B$60*100 -> 0.24412043 | J45: 159005.1 | K45: 163775 | L45: =IF(J45<1,"new",K45/J45-1) -> 0.02999843 | M45: =IF(OR(J45<1,K45<1,B45<=0),"n/a",(C45/K45)/(B45/J45)-1) -> 0.084627034
A46: PIZZAS | B46: 70.663262 | C46: 76.114295 | D46: =C46-B46 -> 5.4510338 | E46: =IF(B46<0.05,"new",C46/B46-1) -> 0.077140988 | F46: =B46/B$60 -> 0.021299604 | G46: =C46/C$60 -> 0.021813064 | H46: =(G46-F46)*100 -> 0.051346037 | I46: =D46/B$60*100 -> 0.16430725 | J46: 107746.84 | K46: 114844 | L46: =IF(J46<1,"new",K46/J46-1) -> 0.065868859 | M46: =IF(OR(J46<1,K46<1,B46<=0),"n/a",(C46/K46)/(B46/J46)-1) -> 0.010575531
... A59: Other small categories (<PHP 0.3M) | B59: 0.041123072 | C59: 0.041026897 | D59: =C59-B59 -> -9.6175038e-05 | E59: =IF(B59<0.05,"new",C59/B59-1) -> new | F59: =B59/B$60 -> 1.2395482e-05 | G59: =C59/C$60 -> 1.1757612e-05 | H59: =(G59-F59)*100 -> -6.3786958e-05 | I59: =D59/B$60*100 -> -2.8989466e-06 | J59: 20160.419 | K59: 11252 | L59: =IF(J59<1,"new",K59/J59-1) -> -0.44187669 | M59: =IF(OR(J59<1,K59<1,B59<=0),"n/a",(C59/K59)/(B59/J59)-1) -> 0.78752843
A60: Total | B60: =SUM(B35:B59) -> 3317.5857 | C60: =SUM(C35:C59) -> 3489.3903 | D60: =SUM(D35:D59) -> 171.80461 | E60: =C60/B60-1 -> 0.051786036 | I60: =SUM(I35:I59) -> 5.1786036 | J60: =SUM(J35:J59) -> 15054344 | K60: =SUM(K35:K59) -> 15428967 | L60: =K60/J60-1 -> 0.02488468 | M60: =(C60/K60)/(B60/J60)-1 -> 0.026248178
A63: C. KIOSK & OTHERS - ALL STORES
A64: Category | B64: 2025 YTD | C64: 2026 YTD | D64: Change | E64: Growth % | F64: Mix 2025 | G64: Mix 2026 | H64: Mix shift (pp) | I64: Contribution to channel growth (pp) | J64: Qty 2025 | K64: Qty 2026 | L64: Qty growth % | M64: Avg price growth %
A65: CHEESE ROLLS* | B65: 92.810197 | C65: 91.067846 | D65: =C65-B65 -> -1.7423519 | E65: =IF(B65<0.05,"new",C65/B65-1) -> -0.01877328 | F65: =B65/B$97 -> 0.23591986 | G65: =C65/C$97 -> 0.24572613 | H65: =(G65-F65)*100 -> 0.98062697 | I65: =D65/B$97*100 -> -0.44289897 | J65: 263655.61 | K65: 250778.59 | L65: =IF(J65<1,"new",K65/J65-1) -> -0.048840314 | M65: =IF(OR(J65<1,K65<1,B65<=0),"n/a",(C65/K65)/(B65/J65)-1) -> 0.031610921
A66: GRABFOOD | B66: 59.578254 | C66: 52.06511 | D66: =C66-B66 -> -7.5131445 | E66: =IF(B66<0.05,"new",C66/B66-1) -> -0.12610548 | F66: =B66/B$97 -> 0.15144557 | G66: =C66/C$97 -> 0.14048601 | H66: =(G66-F66)*100 -> -1.0959566 | I66: =D66/B$97*100 -> -1.9098117 | J66: 75740.323 | K66: 68523 | L66: =IF(J66<1,"new",K66/J66-1) -> -0.09529036 | M66: =IF(OR(J66<1,K66<1,B66<=0),"n/a",(C66/K66)/(B66/J66)-1) -> -0.034060789
A67: ENSAYMADA | B67: 48.680686 | C67: 43.825871 | D67: =C67-B67 -> -4.8548151 | E67: =IF(B67<0.05,"new",C67/B67-1) -> -0.099727747 | F67: =B67/B$97 -> 0.12374438 | G67: =C67/C$97 -> 0.11825427 | H67: =(G67-F67)*100 -> -0.54901129 | I67: =D67/B$97*100 -> -1.2340749 | J67: 129465.35 | K67: 113662 | L67: =IF(J67<1,"new",K67/J67-1) -> -0.12206628 | M67: =IF(OR(J67<1,K67<1,B67<=0),"n/a",(C67/K67)/(B67/J67)-1) -> 0.025444446
A68: TRUFFLE* | B68: 28.922001 | C68: 25.716285 | D68: =C68-B68 -> -3.2057162 | E68: =IF(B68<0.05,"new",C68/B68-1) -> -0.11084005 | F68: =B68/B$97 -> 0.073518587 | G68: =C68/C$97 -> 0.069389621 | H68: =(G68-F68)*100 -> -0.41289661 | I68: =D68/B$97*100 -> -0.81488041 | J68: 31614.323 | K68: 27894.511 | L68: =IF(J68<1,"new",K68/J68-1) -> -0.11766224 | M68: =IF(OR(J68<1,K68<1,B68<=0),"n/a",(C68/K68)/(B68/J68)-1) -> 0.0077319406
A69: SANSRIVAL* | B69: 25.904067 | C69: 21.410261 | D69: =C69-B69 -> -4.4938066 | E69: =IF(B69<0.05,"new",C69/B69-1) -> -0.1734788 | F69: =B69/B$97 -> 0.065847117 | G69: =C69/C$97 -> 0.05777078 | H69: =(G69-F69)*100 -> -0.80763367 | I69: =D69/B$97*100 -> -1.1423079 | J69: 26997.065 | K69: 21482.602 | L69: =IF(J69<1,"new",K69/J69-1) -> -0.20426156 | M69: =IF(OR(J69<1,K69<1,B69<=0),"n/a",(C69/K69)/(B69/J69)-1) -> 0.038684523
A70: SIGNATURE CAKES* | B70: 17.559059 | C70: 17.272808 | D70: =C70-B70 -> -0.28625064 | E70: =IF(B70<0.05,"new",C70/B70-1) -> -0.016302163 | F70: =B70/B$97 -> 0.044634435 | G70: =C70/C$97 -> 0.046606794 | H70: =(G70-F70)*100 -> 0.19723591 | I70: =D70/B$97*100 -> -0.072763784 | J70: 13318.065 | K70: 13828.572 | L70: =IF(J70<1,"new",K70/J70-1) -> 0.038331937 | M70: =IF(OR(J70<1,K70<1,B70<=0),"n/a",(C70/K70)/(B70/J70)-1) -> -0.052617182
A71: BLACK VELVET | B71: 15.99653 | C71: 14.164246 | D71: =C71-B71 -> -1.8322834 | E71: =IF(B71<0.05,"new",C71/B71-1) -> -0.11454256 | F71: =B71/B$97 -> 0.040662547 | G71: =C71/C$97 -> 0.038219037 | H71: =(G71-F71)*100 -> -0.24435098 | I71: =D71/B$97*100 -> -0.46575922 | J71: 19988.774 | K71: 17747 | L71: =IF(J71<1,"new",K71/J71-1) -> -0.11215166 | M71: =IF(OR(J71<1,K71<1,B71<=0),"n/a",(C71/K71)/(B71/J71)-1) -> -0.0026929155
A72: SEA SALT CARAMEL VANILLA* | B72: 14.638036 | C72: 13.841637 | D72: =C72-B72 -> -0.796399 | E72: =IF(B72<0.05,"new",C72/B72-1) -> -0.054406136 | F72: =B72/B$97 -> 0.037209311 | G72: =C72/C$97 -> 0.03734855 | H72: =(G72-F72)*100 -> 0.013923904 | I72: =D72/B$97*100 -> -0.20244149 | J72: 14869.935 | K72: 13506.416 | L72: =IF(J72<1,"new",K72/J72-1) -> -0.091696367 | M72: =IF(OR(J72<1,K72<1,B72<=0),"n/a",(C72/K72)/(B72/J72)-1) -> 0.041054808
A73: CHOCOLATE | B73: 13.314528 | C73: 13.418638 | D73: =C73-B73 -> 0.10411047 | E73: =IF(B73<0.05,"new",C73/B73-1) -> 0.0078193137 | F73: =B73/B$97 -> 0.033845005 | G73: =C73/C$97 -> 0.036207182 | H73: =(G73-F73)*100 -> 0.23621776 | I73: =D73/B$97*100 -> 0.026464471 | J73: 19783.871 | K73: 20167 | L73: =IF(J73<1,"new",K73/J73-1) -> 0.019365726 | M73: =IF(OR(J73<1,K73<1,B73<=0),"n/a",(C73/K73)/(B73/J73)-1) -> -0.011327056
A74: CHRISTMAS | B74: 12.212078 | C74: 10.750505 | D74: =C74-B74 -> -1.4615733 | E74: =IF(B74<0.05,"new",C74/B74-1) -> -0.1196826 | F74: =B74/B$97 -> 0.031042622 | G74: =C74/C$97 -> 0.029007824 | H74: =(G74-F74)*100 -> -0.20347979 | I74: =D74/B$97*100 -> -0.37152618 | J74: 29155.581 | K74: 24386 | L74: =IF(J74<1,"new",K74/J74-1) -> -0.16359066 | M74: =IF(OR(J74<1,K74<1,B74<=0),"n/a",(C74/K74)/(B74/J74)-1) -> 0.052495892
A75: CARROT CAKE | B75: 4.0059805 | C75: 10.478443 | D75: =C75-B75 -> 6.4724621 | E75: =IF(B75<0.05,"new",C75/B75-1) -> 1.6156998 | F75: =B75/B$97 -> 0.010183045 | G75: =C75/C$97 -> 0.028273725 | H75: =(G75-F75)*100 -> 1.809068 | I75: =D75/B$97*100 -> 1.6452743 | J75: 2852.7097 | K75: 11883 | L75: =IF(J75<1,"new",K75/J75-1) -> 3.1655133 | M75: =IF(OR(J75<1,K75<1,B75<=0),"n/a",(C75/K75)/(B75/J75)-1) -> -0.37205821
A76: DESSERT BARS* | B76: 0.59076806 | C76: 10.322727 | D76: =C76-B76 -> 9.7319592 | E76: =IF(B76<0.05,"new",C76/B76-1) -> 16.473401 | F76: =B76/B$97 -> 0.0015017091 | G76: =C76/C$97 -> 0.027853561 | H76: =(G76-F76)*100 -> 2.6351852 | I76: =D76/B$97*100 -> 2.4738256 | J76: 3291.8065 | K76: 24810.876 | L76: =IF(J76<1,"new",K76/J76-1) -> 6.5371611 | M76: =IF(OR(J76<1,K76<1,B76<=0),"n/a",(C76/K76)/(B76/J76)-1) -> 1.3183001
... A96: Other small categories (<PHP 0.3M) | B96: 1.0365846 | C96: 0.80272212 | D96: =C96-B96 -> -0.23386244 | E96: =IF(B96<0.05,"new",C96/B96-1) -> -0.22560865 | F96: =B96/B$97 -> 0.0026349571 | G96: =C96/C$97 -> 0.0021659654 | H96: =(G96-F96)*100 -> -0.046899169 | I96: =D96/B$97*100 -> -0.05944691 | J96: 39137.871 | K96: 25498.826 | L96: =IF(J96<1,"new",K96/J96-1) -> -0.34848714 | M96: =IF(OR(J96<1,K96<1,B96<=0),"n/a",(C96/K96)/(B96/J96)-1) -> 0.18860486
A97: Total | B97: =SUM(B65:B96) -> 393.39713 | C97: =SUM(C65:C96) -> 370.60709 | D97: =SUM(D65:D96) -> -22.790048 | E97: =C97/B97-1 -> -0.057931402 | I97: =SUM(I65:I96) -> -5.7931402 | J97: =SUM(J65:J96) -> 944211.23 | K97: =SUM(K65:K96) -> 867285.53 | L97: =K97/J97-1 -> -0.081470855 | M97: =(C97/K97)/(B97/J97)-1 -> 0.025627333

Sheet Pareto_Categories
A1: Pareto of what is still to come: projected Oct 20-Dec 31, 2026 net sales by category (PHP millions)
A2: Category level (item-level names need the item extract). Projection = Q3-2026 monthly run-rate x category seasonal index (Same-Store 2025 Oct 20-Dec 31 / Q3 month; channel index if the category was too small; limited to 0.8x-1.25x of the channel index so a ramping category cannot distort it), scaled to the Model total. Kiosk lines with a 0 run-rate were not selling in Q3.
A3: Scale factor to tie to Model remainder | C3: =Model!J19/SUM(F6:F84) -> 1.0154471
A5: Rank | B5: Channel | C5: Category | D5: Q3'26 avg / month | E5: Seasonal index | F5: Raw remainder | G5: Projected remainder 2026 | H5: Share of remainder | I5: Cumulative share | J5: Pareto class | K5: YTD change vs 2025 (PHP M) | L5: YTD growth rank | M5: Same days 2025 (PHP M) | N5: Implied YoY on remainder
A6: =ROW()-5 -> 1 | B6: Cafe | C6: ALL-DAY BREAKFAST | D6: 67.886546 | E6: 2.7942291 | F6: =D6*E6 -> 189.69056 | G6: =F6*$C$3 -> 192.62073 | H6: =G6/SUM(G$6:G$84) -> 0.16650323 | I6: =SUM(H$6:H6) -> 0.16650323 | J6: =IF(I6-H6<0.8,"A - top 80%",IF(I6-H6<0.95,"B - next 15%","C - tail")) -> A - top 80% | K6: 35.047643 | L6: =RANK(K6,K$6:K$84) -> 1 | M6: 176.67429 | N6: =IF(M6<0.05,"n/a",G6/M6-1) -> 0.090258978
A7: =ROW()-5 -> 2 | B7: Cafe | C7: SIGNATURE CAKES | D7: 58.044959 | E7: 2.9718006 | F7: =D7*E7 -> 172.49804 | G7: =F7*$C$3 -> 175.16264 | H7: =G7/SUM(G$6:G$84) -> 0.15141228 | I7: =SUM(H$6:H7) -> 0.31791551 | J7: =IF(I7-H7<0.8,"A - top 80%",IF(I7-H7<0.95,"B - next 15%","C - tail")) -> A - top 80% | K7: 30.943399 | L7: =RANK(K7,K$6:K$84) -> 2 | M7: 174.47961 | N7: =IF(M7<0.05,"n/a",G7/M7-1) -> 0.0039146916
A8: =ROW()-5 -> 3 | B8: Cafe | C8: FLAVORFUL PASTAS | D8: 53.910192 | E8: 2.7767363 | F8: =D8*E8 -> 149.69439 | G8: =F8*$C$3 -> 152.00674 | H8: =G8/SUM(G$6:G$84) -> 0.13139609 | I8: =SUM(H$6:H8) -> 0.4493116 | J8: =IF(I8-H8<0.8,"A - top 80%",IF(I8-H8<0.95,"B - next 15%","C - tail")) -> A - top 80% | K8: 14.883674 | L8: =RANK(K8,K$6:K$84) -> 4 | M8: 145.75647 | N8: =IF(M8<0.05,"n/a",G8/M8-1) -> 0.042881588
A9: =ROW()-5 -> 4 | B9: Cafe | C9: BEVERAGES | D9: 43.287481 | E9: 2.7327911 | F9: =D9*E9 -> 118.29564 | G9: =F9*$C$3 -> 120.12297 | H9: =G9/SUM(G$6:G$84) -> 0.10383546 | I9: =SUM(H$6:H9) -> 0.55314706 | J9: =IF(I9-H9<0.8,"A - top 80%",IF(I9-H9<0.95,"B - next 15%","C - tail")) -> A - top 80% | K9: 27.000475 | L9: =RANK(K9,K$6:K$84) -> 3 | M9: 109.51366 | N9: =IF(M9<0.05,"n/a",G9/M9-1) -> 0.096876628
A10: =ROW()-5 -> 5 | B10: Cafe | C10: CHEESE ROLLS | D10: 28.848082 | E10: 2.7615173 | F10: =D10*E10 -> 79.664479 | G10: =F10*$C$3 -> 80.895066 | H10: =G10/SUM(G$6:G$84) -> 0.069926477 | I10: =SUM(H$6:H10) -> 0.62307354 | J10: =IF(I10-H10<0.8,"A - top 80%",IF(I10-H10<0.95,"B - next 15%","C - tail")) -> A - top 80% | K10: 12.256936 | L10: =RANK(K10,K$6:K$84) -> 7 | M10: 73.424888 | N10: =IF(M10<0.05,"n/a",G10/M10-1) -> 0.10173903
A11: =ROW()-5 -> 6 | B11: Cafe | C11: ENSAYMADAS | D11: 18.904528 | E11: 2.6618496 | F11: =D11*E11 -> 50.321009 | G11: =F11*$C$3 -> 51.098323 | H11: =G11/SUM(G$6:G$84) -> 0.044169885 | I11: =SUM(H$6:H11) -> 0.66724342 | J11: =IF(I11-H11<0.8,"A - top 80%",IF(I11-H11<0.95,"B - next 15%","C - tail")) -> A - top 80% | K11: -5.6376392 | L11: =RANK(K11,K$6:K$84) -> 75 | M11: 51.906129 | N11: =IF(M11<0.05,"n/a",G11/M11-1) -> -0.015562826
A12: =ROW()-5 -> 7 | B12: Cafe | C12: FRESH SALADS | D12: 13.882975 | E12: 2.7651225 | F12: =D12*E12 -> 38.388126 | G12: =F12*$C$3 -> 38.981112 | H12: =G12/SUM(G$6:G$84) -> 0.03369565 | I12: =SUM(H$6:H12) -> 0.70093907 | J12: =IF(I12-H12<0.8,"A - top 80%",IF(I12-H12<0.95,"B - next 15%","C - tail")) -> A - top 80% | K12: 3.3717252 | L12: =RANK(K12,K$6:K$84) -> 19 | M12: 37.379827 | N12: =IF(M12<0.05,"n/a",G12/M12-1) -> 0.042838189
A13: =ROW()-5 -> 8 | B13: Cafe | C13: PERFECT PLATES | D13: 11.896519 | E13: 2.755708 | F13: =D13*E13 -> 32.783332 | G13: =F13*$C$3 -> 33.28974 | H13: =G13/SUM(G$6:G$84) -> 0.028775974 | I13: =SUM(H$6:H13) -> 0.72971505 | J13: =IF(I13-H13<0.8,"A - top 80%",IF(I13-H13<0.95,"B - next 15%","C - tail")) -> A - top 80% | K13: -7.3185866 | L13: =RANK(K13,K$6:K$84) -> 78 | M13: 38.891507 | N13: =IF(M13<0.05,"n/a",G13/M13-1) -> -0.14403574
A14: =ROW()-5 -> 9 | B14: Cafe | C14: MAINS | D14: 10.406714 | E14: 2.9512511 | F14: =D14*E14 -> 30.712825 | G14: =F14*$C$3 -> 31.18725 | H14: =G14/SUM(G$6:G$84) -> 0.026958561 | I14: =SUM(H$6:H14) -> 0.75667361 | J14: =IF(I14-H14<0.8,"A - top 80%",IF(I14-H14<0.95,"B - next 15%","C - tail")) -> A - top 80% | K14: 12.661802 | L14: =RANK(K14,K$6:K$84) -> 6 | M14: 29.715536 | N14: =IF(M14<0.05,"n/a",G14/M14-1) -> 0.049526744
A15: =ROW()-5 -> 10 | B15: Kiosk & Others | C15: CHEESE ROLLS | D15: 9.2459312 | E15: 3.0070491 | F15: =D15*E15 -> 27.802969 | G15: =F15*$C$3 -> 28.232445 | H15: =G15/SUM(G$6:G$84) -> 0.024404399 | I15: =SUM(H$6:H15) -> 0.78107801 | J15: =IF(I15-H15<0.8,"A - top 80%",IF(I15-H15<0.95,"B - next 15%","C - tail")) -> A - top 80% | K15: -1.7423519 | L15: =RANK(K15,K$6:K$84) -> 67 | M15: 26.580128 | N15: =IF(M15<0.05,"n/a",G15/M15-1) -> 0.062163614
A16: =ROW()-5 -> 11 | B16: Cafe | C16: SOUPS | D16: 9.0858126 | E16: 2.8371128 | F16: =D16*E16 -> 25.777475 | G16: =F16*$C$3 -> 26.175663 | H16: =G16/SUM(G$6:G$84) -> 0.022626496 | I16: =SUM(H$6:H16) -> 0.8037045 | J16: =IF(I16-H16<0.8,"A - top 80%",IF(I16-H16<0.95,"B - next 15%","C - tail")) -> A - top 80% | K16: 6.9009647 | L16: =RANK(K16,K$6:K$84) -> 11 | M16: 22.460457 | N16: =IF(M16<0.05,"n/a",G16/M16-1) -> 0.16541097
A17: =ROW()-5 -> 12 | B17: Cafe | C17: PIZZAS | D17: 7.3772327 | E17: 3.0978434 | F17: =D17*E17 -> 22.853512 | G17: =F17*$C$3 -> 23.206533 | H17: =G17/SUM(G$6:G$84) -> 0.020059951 | I17: =SUM(H$6:H17) -> 0.82376445 | J17: =IF(I17-H17<0.8,"A - top 80%",IF(I17-H17<0.95,"B - next 15%","C - tail")) -> B - next 15% | K17: 5.4510338 | L17: =RANK(K17,K$6:K$84) -> 13 | M17: 22.075733 | N17: =IF(M17<0.05,"n/a",G17/M17-1) -> 0.051223664
... A84: =ROW()-5 -> 79 | B84: Kiosk & Others | C84: VALENTINES CAKE | D84: 0 | E84: 3.5363667 | F84: =D84*E84 -> 0 | G84: =F84*$C$3 -> 0 | H84: =G84/SUM(G$6:G$84) -> 0 | I84: =SUM(H$6:H84) -> 1 | J84: =IF(I84-H84<0.8,"A - top 80%",IF(I84-H84<0.95,"B - next 15%","C - tail")) -> C - tail | K84: -1.3904956 | L84: =RANK(K84,K$6:K$84) -> 65 | M84: 0 | N84: =IF(M84<0.05,"n/a",G84/M84-1) -> n/a
C85: Total | G85: =SUM(G6:G84) -> 1156.8589 | H85: =SUM(H6:H84) -> 1 | K85: =SUM(K6:K84) -> 149.01456 | M85: =SUM(M6:M84) -> 1119.5474
C87: Categories in class A (drive ~80%) | G87: =COUNTIF(J6:J84,"A*") -> 11
C88: Share of all categories | G88: =G87/COUNTA(C6:C84) -> 0.13924051
C89: Share of remainder they deliver | G89: =SUMIF(J6:J84,"A*",G6:G84)/G85 -> 0.8037045
A92: Top contributors to YTD growth (descending) and biggest drags
A93: Rank | B93: Channel | C93: Category | D93: YTD change (PHP M) | E93: Share of net YTD growth
A94: 1 | B94: Cafe | C94: ALL-DAY BREAKFAST | D94: =K6 -> 35.047643 | E94: =D94/YTD_SOG!$D$11 -> 0.23519609
A95: 2 | B95: Cafe | C95: SIGNATURE CAKES | D95: =K7 -> 30.943399 | E95: =D95/YTD_SOG!$D$11 -> 0.20765352
A96: 3 | B96: Cafe | C96: BEVERAGES | D96: =K9 -> 27.000475 | E96: =D96/YTD_SOG!$D$11 -> 0.18119353
A97: 4 | B97: Cafe | C97: FLAVORFUL PASTAS | D97: =K8 -> 14.883674 | E97: =D97/YTD_SOG!$D$11 -> 0.09988067
A98: 5 | B98: Cafe | C98: PASTRIES | D98: =K21 -> 13.654113 | E98: =D98/YTD_SOG!$D$11 -> 0.091629389
A99: 6 | B99: Cafe | C99: MAINS | D99: =K14 -> 12.661802 | E99: =D99/YTD_SOG!$D$11 -> 0.084970231
A100: 7 | B100: Cafe | C100: CHEESE ROLLS | D100: =K10 -> 12.256936 | E100: =D100/YTD_SOG!$D$11 -> 0.082253278
A101: 8 | B101: Kiosk & Others | C101: DESSERT BARS | D101: =K37 -> 9.7319592 | E101: =D101/YTD_SOG!$D$11 -> 0.065308779
A102: 9 | B102: Cafe | C102: HEARTY SANDWICHES | D102: =K18 -> 8.0989046 | E102: =D102/YTD_SOG!$D$11 -> 0.054349752
A103: 10 | B103: Cafe | C103: DESSERT BARS | D103: =K22 -> 7.5598439 | E103: =D103/YTD_SOG!$D$11 -> 0.050732249
A104: 11 | B104: Cafe | C104: SOUPS | D104: =K16 -> 6.9009647 | E104: =D104/YTD_SOG!$D$11 -> 0.046310673
A105: 12 | B105: Kiosk & Others | C105: CARROT CAKE | D105: =K33 -> 6.4724621 | E105: =D105/YTD_SOG!$D$11 -> 0.043435098
A106: Drag 1 | B106: Kiosk & Others | C106: GRABFOOD | D106: =K20 -> -7.5131445 | E106: =D106/YTD_SOG!$D$11 -> -0.050418861
A107: Drag 2 | B107: Cafe | C107: PERFECT PLATES | D107: =K13 -> -7.3185866 | E107: =D107/YTD_SOG!$D$11 -> -0.04911323
A108: Drag 3 | B108: Kiosk & Others | C108: MARY GRACE MAMON | D108: =K63 -> -6.0159126 | E108: =D108/YTD_SOG!$D$11 -> -0.040371306
A109: Drag 4 | B109: Kiosk & Others | C109: BROWNIE | D109: =K76 -> -5.7443106 | E109: =D109/YTD_SOG!$D$11 -> -0.038548652
A110: Drag 5 | B110: Cafe | C110: ENSAYMADAS | D110: =K11 -> -5.6376392 | E110: =D110/YTD_SOG!$D$11 -> -0.037832807
A111: Drag 6 | B111: Kiosk & Others | C111: ENSAYMADA | D111: =K24 -> -4.8548151 | E111: =D111/YTD_SOG!$D$11 -> -0.032579467
A112: Drag 7 | B112: Kiosk & Others | C112: LEMON BARS | D112: =K68 -> -4.8146085 | E112: =D112/YTD_SOG!$D$11 -> -0.032309651
A113: Drag 8 | B113: Kiosk & Others | C113: SANSRIVAL | D113: =K26 -> -4.4938066 | E113: =D113/YTD_SOG!$D$11 -> -0.030156828

Sheet Pareto_Items
A1: Item-level Pareto: which items carry the remaining Oct 20-Dec 31, 2026 revenue (PHP millions) - PROVISIONAL
A2: Ranked by revenue (no cost data available, so this is revenue contribution, not margin). Item revenue = unit price / 1.12 x qty (ex-VAT, team definition). Each category's projected remainder (Pareto_Categories, VAT-inclusive net basis) is shared out across its items by July-2026 revenue. Growth = Jan+Jul 2026 vs Jan+Jul 2025 (the only complete months in the item export).
A3: Priority tier: 1 PROTECT = top-80% item, stable or growing | 2 FIX = top-80% item down more than 5% | 3 SCALE = outside top 80%, new or up 25%+ (min PHP 0.3M in 2 months) | 4 MAINTAIN = the rest.
A5: Rank | B5: Item code | C5: Item name | D5: Channel | E5: Category | F5: Jul 2026 revenue ex-VAT (PHP) | G5: Share within category | H5: Category remainder (PHP M) | I5: Projected remainder (PHP M) | J5: Share of remainder | K5: Cumulative share | L5: Pareto class | M5: Jan+Jul 2025 revenue ex-VAT (PHP) | N5: Jan+Jul 2026 revenue ex-VAT (PHP) | O5: Change (PHP) | P5: Growth % | Q5: Priority tier | R5: Growth % (numeric)
A6: =ROW()-5 -> 1 | B6: ADB-SBT1 | C6: SIRLOIN BEEF TAPA - PLATE | D6: Cafe | E6: ALL-DAY BREAKFAST | F6: 20687440 | G6: =IF(SUMIFS(F$6:F$473,D$6:D$473,D6,E$6:E$473,E6)=0,0,F6/SUMIFS(F$6:F$473,D$6:D$473,D6,E$6:E$473,E6)) -> 0.36084638 | H6: =SUMIFS(Pareto_Categories!$G$6:$G$84,Pareto_Categories!$B$6:$B$84,D6,Pareto_Categories!$C$6:$C$84,E6) -> 192.62073 | I6: =G6*H6 -> 69.506494 | J6: =I6/$I$475 -> 0.060082061 | K6: =SUM(J$6:J6) -> 0.060082061 | L6: =IF(I6<=0,"-",IF(K6-J6<0.8,"A - top 80%",IF(K6-J6<0.95,"B - next 15%","C - tail"))) -> A - top 80% | M6: 38097259 | N6: 41717503 | O6: =N6-M6 -> 3620244.1 | P6: =IF(M6<1000,"new",R6) -> 0.095026366 | Q6: =IF(LEFT(L6,1)="A",IF(R6<-0.05,"2 FIX","1 PROTECT"),IF(AND(N6>=300000,OR(P6="new",R6>=0.25),LEFT(L6,1)<>"-"),"3 SCALE","4 MAINTAIN")) -> 1 PROTECT | R6: =IF(M6<1000,0,N6/M6-1) -> 0.095026366
A7: =ROW()-5 -> 2 | B7: CRC-MGCR12 | C7: MARY GRACE CHEESEROLLS - BOX OF 12 | D7: Cafe | E7: CHEESE ROLLS | F7: 13855322 | G7: =IF(SUMIFS(F$6:F$473,D$6:D$473,D7,E$6:E$473,E7)=0,0,F7/SUMIFS(F$6:F$473,D$6:D$473,D7,E$6:E$473,E7)) -> 0.52805774 | H7: =SUMIFS(Pareto_Categories!$G$6:$G$84,Pareto_Categories!$B$6:$B$84,D7,Pareto_Categories!$C$6:$C$84,E7) -> 80.895066 | I7: =G7*H7 -> 42.717265 | J7: =I7/$I$475 -> 0.036925202 | K7: =SUM(J$6:J7) -> 0.097007263 | L7: =IF(I7<=0,"-",IF(K7-J7<0.8,"A - top 80%",IF(K7-J7<0.95,"B - next 15%","C - tail"))) -> A - top 80% | M7: 27076342 | N7: 28301545 | O7: =N7-M7 -> 1225202.7 | P7: =IF(M7<1000,"new",R7) -> 0.045249934 | Q7: =IF(LEFT(L7,1)="A",IF(R7<-0.05,"2 FIX","1 PROTECT"),IF(AND(N7>=300000,OR(P7="new",R7>=0.25),LEFT(L7,1)<>"-"),"3 SCALE","4 MAINTAIN")) -> 1 PROTECT | R7: =IF(M7<1000,0,N7/M7-1) -> 0.045249934
A8: =ROW()-5 -> 3 | B8: ADB-SALPI1 | C8: RIB-EYE SALPICAO AND EGGS - PLATE | D8: Cafe | E8: ALL-DAY BREAKFAST | F8: 10469155 | G8: =IF(SUMIFS(F$6:F$473,D$6:D$473,D8,E$6:E$473,E8)=0,0,F8/SUMIFS(F$6:F$473,D$6:D$473,D8,E$6:E$473,E8)) -> 0.18261111 | H8: =SUMIFS(Pareto_Categories!$G$6:$G$84,Pareto_Categories!$B$6:$B$84,D8,Pareto_Categories!$C$6:$C$84,E8) -> 192.62073 | I8: =G8*H8 -> 35.174687 | J8: =I8/$I$475 -> 0.030405327 | K8: =SUM(J$6:J8) -> 0.12741259 | L8: =IF(I8<=0,"-",IF(K8-J8<0.8,"A - top 80%",IF(K8-J8<0.95,"B - next 15%","C - tail"))) -> A - top 80% | M8: 23052841 | N8: 21836445 | O8: =N8-M8 -> -1216396 | P8: =IF(M8<1000,"new",R8) -> -0.052765556 | Q8: =IF(LEFT(L8,1)="A",IF(R8<-0.05,"2 FIX","1 PROTECT"),IF(AND(N8>=300000,OR(P8="new",R8>=0.25),LEFT(L8,1)<>"-"),"3 SCALE","4 MAINTAIN")) -> 2 FIX | R8: =IF(M8<1000,0,N8/M8-1) -> -0.052765556
A9: =ROW()-5 -> 4 | B9: ADB-FBB1 | C9: DAING NA BANGUS - PLATE | D9: Cafe | E9: ALL-DAY BREAKFAST | F9: 10033653 | G9: =IF(SUMIFS(F$6:F$473,D$6:D$473,D9,E$6:E$473,E9)=0,0,F9/SUMIFS(F$6:F$473,D$6:D$473,D9,E$6:E$473,E9)) -> 0.17501476 | H9: =SUMIFS(Pareto_Categories!$G$6:$G$84,Pareto_Categories!$B$6:$B$84,D9,Pareto_Categories!$C$6:$C$84,E9) -> 192.62073 | I9: =G9*H9 -> 33.711471 | J9: =I9/$I$475 -> 0.029140509 | K9: =SUM(J$6:J9) -> 0.1565531 | L9: =IF(I9<=0,"-",IF(K9-J9<0.8,"A - top 80%",IF(K9-J9<0.95,"B - next 15%","C - tail"))) -> A - top 80% | M9: 18534805 | N9: 20830875 | O9: =N9-M9 -> 2296070.9 | P9: =IF(M9<1000,"new",R9) -> 0.12387888 | Q9: =IF(LEFT(L9,1)="A",IF(R9<-0.05,"2 FIX","1 PROTECT"),IF(AND(N9>=300000,OR(P9="new",R9>=0.25),LEFT(L9,1)<>"-"),"3 SCALE","4 MAINTAIN")) -> 1 PROTECT | R9: =IF(M9<1000,0,N9/M9-1) -> 0.12387888
A10: =ROW()-5 -> 5 | B10: CRC-MGCR1 | C10: MARY GRACE CHEESEROLLS - PC | D10: Kiosk & Others | E10: CHEESE ROLLS | F10: 1000682.1 | G10: =IF(SUMIFS(F$6:F$473,D$6:D$473,D10,E$6:E$473,E10)=0,0,F10/SUMIFS(F$6:F$473,D$6:D$473,D10,E$6:E$473,E10)) -> 0.98888265 | H10: =SUMIFS(Pareto_Categories!$G$6:$G$84,Pareto_Categories!$B$6:$B$84,D10,Pareto_Categories!$C$6:$C$84,E10) -> 28.232445 | I10: =G10*H10 -> 27.918575 | J10: =I10/$I$475 -> 0.024133076 | K10: =SUM(J$6:J10) -> 0.18068618 | L10: =IF(I10<=0,"-",IF(K10-J10<0.8,"A - top 80%",IF(K10-J10<0.95,"B - next 15%","C - tail"))) -> A - top 80% | M10: 2328171.4 | N10: 2097289.3 | O10: =N10-M10 -> -230882.14 | P10: =IF(M10<1000,"new",R10) -> -0.099168876 | Q10: =IF(LEFT(L10,1)="A",IF(R10<-0.05,"2 FIX","1 PROTECT"),IF(AND(N10>=300000,OR(P10="new",R10>=0.25),LEFT(L10,1)<>"-"),"3 SCALE","4 MAINTAIN")) -> 2 FIX | R10: =IF(M10<1000,0,N10/M10-1) -> -0.099168876
A11: =ROW()-5 -> 6 | B11: FPCR-MGMC1 | C11: MARY GRACE MUSHROOM CREAM - PLATE | D11: Cafe | E11: FLAVORFUL PASTAS | F11: 5178156.2 | G11: =IF(SUMIFS(F$6:F$473,D$6:D$473,D11,E$6:E$473,E11)=0,0,F11/SUMIFS(F$6:F$473,D$6:D$473,D11,E$6:E$473,E11)) -> 0.15336391 | H11: =SUMIFS(Pareto_Categories!$G$6:$G$84,Pareto_Categories!$B$6:$B$84,D11,Pareto_Categories!$C$6:$C$84,E11) -> 152.00674 | I11: =G11*H11 -> 23.312348 | J11: =I11/$I$475 -> 0.02015141 | K11: =SUM(J$6:J11) -> 0.20083759 | L11: =IF(I11<=0,"-",IF(K11-J11<0.8,"A - top 80%",IF(K11-J11<0.95,"B - next 15%","C - tail"))) -> A - top 80% | M11: 10702272 | N11: 10597178 | O11: =N11-M11 -> -105094.71 | P11: =IF(M11<1000,"new",R11) -> -0.0098198504 | Q11: =IF(LEFT(L11,1)="A",IF(R11<-0.05,"2 FIX","1 PROTECT"),IF(AND(N11>=300000,OR(P11="new",R11>=0.25),LEFT(L11,1)<>"-"),"3 SCALE","4 MAINTAIN")) -> 1 PROTECT | R11: =IF(M11<1000,0,N11/M11-1) -> -0.0098198504
A12: =ROW()-5 -> 7 | B12: ADB-TVL1 | C12: TOASTED VIGAN LONGGANISA - PLATE | D12: Cafe | E12: ALL-DAY BREAKFAST | F12: 6802920.2 | G12: =IF(SUMIFS(F$6:F$473,D$6:D$473,D12,E$6:E$473,E12)=0,0,F12/SUMIFS(F$6:F$473,D$6:D$473,D12,E$6:E$473,E12)) -> 0.11866181 | H12: =SUMIFS(Pareto_Categories!$G$6:$G$84,Pareto_Categories!$B$6:$B$84,D12,Pareto_Categories!$C$6:$C$84,E12) -> 192.62073 | I12: =G12*H12 -> 22.856725 | J12: =I12/$I$475 -> 0.019757566 | K12: =SUM(J$6:J12) -> 0.22059515 | L12: =IF(I12<=0,"-",IF(K12-J12<0.8,"A - top 80%",IF(K12-J12<0.95,"B - next 15%","C - tail"))) -> A - top 80% | M12: 7363075.9 | N12: 10556091 | O12: =N12-M12 -> 3193014.9 | P12: =IF(M12<1000,"new",R12) -> 0.43365231 | Q12: =IF(LEFT(L12,1)="A",IF(R12<-0.05,"2 FIX","1 PROTECT"),IF(AND(N12>=300000,OR(P12="new",R12>=0.25),LEFT(L12,1)<>"-"),"3 SCALE","4 MAINTAIN")) -> 1 PROTECT | R12: =IF(M12<1000,0,N12/M12-1) -> 0.43365231
A13: =ROW()-5 -> 8 | B13: FPOL-SLS1 | C13: SPICY LEMON SCAMPI - PLATE | D13: Cafe | E13: FLAVORFUL PASTAS | F13: 5059815.5 | G13: =IF(SUMIFS(F$6:F$473,D$6:D$473,D13,E$6:E$473,E13)=0,0,F13/SUMIFS(F$6:F$473,D$6:D$473,D13,E$6:E$473,E13)) -> 0.14985896 | H13: =SUMIFS(Pareto_Categories!$G$6:$G$84,Pareto_Categories!$B$6:$B$84,D13,Pareto_Categories!$C$6:$C$84,E13) -> 152.00674 | I13: =G13*H13 -> 22.779571 | J13: =I13/$I$475 -> 0.019690873 | K13: =SUM(J$6:J13) -> 0.24028603 | L13: =IF(I13<=0,"-",IF(K13-J13<0.8,"A - top 80%",IF(K13-J13<0.95,"B - next 15%","C - tail"))) -> A - top 80% | M13: 8780450.4 | N13: 9878782.1 | O13: =N13-M13 -> 1098331.7 | P13: =IF(M13<1000,"new",R13) -> 0.1250883 | Q13: =IF(LEFT(L13,1)="A",IF(R13<-0.05,"2 FIX","1 PROTECT"),IF(AND(N13>=300000,OR(P13="new",R13>=0.25),LEFT(L13,1)<>"-"),"3 SCALE","4 MAINTAIN")) -> 1 PROTECT | R13: =IF(M13<1000,0,N13/M13-1) -> 0.1250883
A14: =ROW()-5 -> 9 | B14: CRC-MGCR6 | C14: MARY GRACE CHEESEROLLS - BOX OF 6 | D14: Cafe | E14: CHEESE ROLLS | F14: 7207227.8 | G14: =IF(SUMIFS(F$6:F$473,D$6:D$473,D14,E$6:E$473,E14)=0,0,F14/SUMIFS(F$6:F$473,D$6:D$473,D14,E$6:E$473,E14)) -> 0.27468379 | H14: =SUMIFS(Pareto_Categories!$G$6:$G$84,Pareto_Categories!$B$6:$B$84,D14,Pareto_Categories!$C$6:$C$84,E14) -> 80.895066 | I14: =G14*H14 -> 22.220563 | J14: =I14/$I$475 -> 0.019207661 | K14: =SUM(J$6:J14) -> 0.25949369 | L14: =IF(I14<=0,"-",IF(K14-J14<0.8,"A - top 80%",IF(K14-J14<0.95,"B - next 15%","C - tail"))) -> A - top 80% | M14: 13696035 | N14: 14553149 | O14: =N14-M14 -> 857113.71 | P14: =IF(M14<1000,"new",R14) -> 0.062581155 | Q14: =IF(LEFT(L14,1)="A",IF(R14<-0.05,"2 FIX","1 PROTECT"),IF(AND(N14>=300000,OR(P14="new",R14>=0.25),LEFT(L14,1)<>"-"),"3 SCALE","4 MAINTAIN")) -> 1 PROTECT | R14: =IF(M14<1000,0,N14/M14-1) -> 0.062581155
A15: =ROW()-5 -> 10 | B15: FPOL-SP1 | C15: SEAFOOD PASTA - PLATE | D15: Cafe | E15: FLAVORFUL PASTAS | F15: 4902422.4 | G15: =IF(SUMIFS(F$6:F$473,D$6:D$473,D15,E$6:E$473,E15)=0,0,F15/SUMIFS(F$6:F$473,D$6:D$473,D15,E$6:E$473,E15)) -> 0.14519737 | H15: =SUMIFS(Pareto_Categories!$G$6:$G$84,Pareto_Categories!$B$6:$B$84,D15,Pareto_Categories!$C$6:$C$84,E15) -> 152.00674 | I15: =G15*H15 -> 22.070978 | J15: =I15/$I$475 -> 0.019078359 | K15: =SUM(J$6:J15) -> 0.27857205 | L15: =IF(I15<=0,"-",IF(K15-J15<0.8,"A - top 80%",IF(K15-J15<0.95,"B - next 15%","C - tail"))) -> A - top 80% | M15: 10003671 | N15: 9983639.2 | O15: =N15-M15 -> -20032.223 | P15: =IF(M15<1000,"new",R15) -> -0.0020024871 | Q15: =IF(LEFT(L15,1)="A",IF(R15<-0.05,"2 FIX","1 PROTECT"),IF(AND(N15>=300000,OR(P15="new",R15>=0.25),LEFT(L15,1)<>"-"),"3 SCALE","4 MAINTAIN")) -> 1 PROTECT | R15: =IF(M15<1000,0,N15/M15-1) -> -0.0020024871
A16: =ROW()-5 -> 11 | B16: BEVHC-MGHC1 | C16: MARY GRACE HOT CHOCOLATE CUP | D16: Cafe | E16: BEVERAGES | F16: 6722915.8 | G16: =IF(SUMIFS(F$6:F$473,D$6:D$473,D16,E$6:E$473,E16)=0,0,F16/SUMIFS(F$6:F$473,D$6:D$473,D16,E$6:E$473,E16)) -> 0.17923396 | H16: =SUMIFS(Pareto_Categories!$G$6:$G$84,Pareto_Categories!$B$6:$B$84,D16,Pareto_Categories!$C$6:$C$84,E16) -> 120.12297 | I16: =G16*H16 -> 21.530115 | J16: =I16/$I$475 -> 0.018610832 | K16: =SUM(J$6:J16) -> 0.29718288 | L16: =IF(I16<=0,"-",IF(K16-J16<0.8,"A - top 80%",IF(K16-J16<0.95,"B - next 15%","C - tail"))) -> A - top 80% | M16: 13614585 | N16: 14631592 | O16: =N16-M16 -> 1017007.4 | P16: =IF(M16<1000,"new",R16) -> 0.074699847 | Q16: =IF(LEFT(L16,1)="A",IF(R16<-0.05,"2 FIX","1 PROTECT"),IF(AND(N16>=300000,OR(P16="new",R16>=0.25),LEFT(L16,1)<>"-"),"3 SCALE","4 MAINTAIN")) -> 1 PROTECT | R16: =IF(M16<1000,0,N16/M16-1) -> 0.074699847
A17: =ROW()-5 -> 12 | B17: PPP-FTHP1 | C17: PERFECT PLATE - FRESH TOMATO & HERB | D17: Cafe | E17: PERFECT PLATES | F17: 7449190.2 | G17: =IF(SUMIFS(F$6:F$473,D$6:D$473,D17,E$6:E$473,E17)=0,0,F17/SUMIFS(F$6:F$473,D$6:D$473,D17,E$6:E$473,E17)) -> 0.60404662 | H17: =SUMIFS(Pareto_Categories!$G$6:$G$84,Pareto_Categories!$B$6:$B$84,D17,Pareto_Categories!$C$6:$C$84,E17) -> 33.28974 | I17: =G17*H17 -> 20.108555 | J17: =I17/$I$475 -> 0.017382022 | K17: =SUM(J$6:J17) -> 0.3145649 | L17: =IF(I17<=0,"-",IF(K17-J17<0.8,"A - top 80%",IF(K17-J17<0.95,"B - next 15%","C - tail"))) -> A - top 80% | M17: 15923136 | N17: 16185136 | O17: =N17-M17 -> 261999.61 | P17: =IF(M17<1000,"new",R17) -> 0.01645402 | Q17: =IF(LEFT(L17,1)="A",IF(R17<-0.05,"2 FIX","1 PROTECT"),IF(AND(N17>=300000,OR(P17="new",R17>=0.25),LEFT(L17,1)<>"-"),"3 SCALE","4 MAINTAIN")) -> 1 PROTECT | R17: =IF(M17<1000,0,N17/M17-1) -> 0.01645402
... A473: =ROW()-5 -> 468 | B473: NFF-DEDIADD | C473: ADDITIONALDEDICATION | D473: Kiosk & Others | E473: WEB CELEBRATION CAKES | F473: 17.857143 | G473: =IF(SUMIFS(F$6:F$473,D$6:D$473,D473,E$6:E$473,E473)=0,0,F473/SUMIFS(F$6:F$473,D$6:D$473,D473,E$6:E$473,E473)) -> 0.00012390038 | H473: =SUMIFS(Pareto_Categories!$G$6:$G$84,Pareto_Categories!$B$6:$B$84,D473,Pareto_Categories!$C$6:$C$84,E473) -> 0.70289936 | I473: =G473*H473 -> 8.70895e-05 | J473: =I473/$I$475 -> 7.5280975e-08 | K473: =SUM(J$6:J473) -> 0.9775098 | L473: =IF(I473<=0,"-",IF(K473-J473<0.8,"A - top 80%",IF(K473-J473<0.95,"B - next 15%","C - tail"))) -> C - tail | M473: 0 | N473: 17.857143 | O473: =N473-M473 -> 17.857143 | P473: =IF(M473<1000,"new",R473) -> new | Q473: =IF(LEFT(L473,1)="A",IF(R473<-0.05,"2 FIX","1 PROTECT"),IF(AND(N473>=300000,OR(P473="new",R473>=0.25),LEFT(L473,1)<>"-"),"3 SCALE","4 MAINTAIN")) -> 4 MAINTAIN | R473: =IF(M473<1000,0,N473/M473-1) -> 0
C474: Kiosk categories with no July-2026 sales (seasonal: Christmas, Fruitcake, etc.) | I474: 26.018 | J474: =I474/$I$475 -> 0.022490202
C475: Total (ties to Model 2026 remainder) | H475: =Model!J19 -> 1156.8589 | I475: =SUM(I6:I474) -> 1156.8594
C477: Items in class A (drive ~80%) | I477: =COUNTIF(L6:L473,"A*") -> 98
C478: Items with projected sales | I478: =COUNTIF(I6:I473,">0") -> 468
C479: Class A as % of items | I479: =I477/I478 -> 0.20940171
C480: Share of remainder delivered by class A | I480: =SUMIF(L6:L473,"A*",I6:I473)/I475 -> 0.80144525

Sheet Item_Priorities
A1: Which items to prioritise to land the PHP 5B (revenue-based, provisional)
A2: Tiers come from Pareto_Items. Sizing = projected remainder x assumed uplift (blue cells). Not a forecast: levers overlap and need execution.
A4: Tier | B4: What it means | C4: Items | D4: Projected remainder (PHP M) | E4: Share of remainder | F4: Assumed uplift | G4: Impact (PHP M)
A5: 1 PROTECT | B5: Top-80% items that are stable or growing: never run out, keep quality and visibility. | C5: =COUNTIF(Pareto_Items!$Q$6:$Q$473,A5) -> 77 | D5: =SUMIF(Pareto_Items!$Q$6:$Q$473,A5,Pareto_Items!$I$6:$I$473) -> 754.87056 | E5: =D5/Pareto_Items!$I$475 -> 0.65251714 | F5: 0 | G5: =D5*F5 -> 0
A6: 2 FIX | B6: Top-80% items down >5% YoY: restore to flat (uplift = their own decline). | C6: =COUNTIF(Pareto_Items!$Q$6:$Q$473,A6) -> 21 | D6: =SUMIF(Pareto_Items!$Q$6:$Q$473,A6,Pareto_Items!$I$6:$I$473) -> 172.28887 | E6: =D6/Pareto_Items!$I$475 -> 0.14892811 | F6: blended | G6: =SUMPRODUCT((Pareto_Items!$Q$6:$Q$473="2 FIX")*Pareto_Items!$I$6:$I$473*(-Pareto_Items!$R$6:$R$473)) -> 15.394625
A7: 3 SCALE | B7: Outside the top 80% but new or growing 25%+: push visibility and bundles. | C7: =COUNTIF(Pareto_Items!$Q$6:$Q$473,A7) -> 47 | D7: =SUMIF(Pareto_Items!$Q$6:$Q$473,A7,Pareto_Items!$I$6:$I$473) -> 67.414106 | E7: =D7/Pareto_Items!$I$475 -> 0.058273381 | F7: 0.15 | G7: =D7*F7 -> 10.112116
A8: 4 MAINTAIN | B8: Everything else: no special action. | C8: =COUNTIF(Pareto_Items!$Q$6:$Q$473,A8) -> 323 | D8: =SUMIF(Pareto_Items!$Q$6:$Q$473,A8,Pareto_Items!$I$6:$I$473) -> 136.26782 | E8: =D8/Pareto_Items!$I$475 -> 0.11779117 | F8: 0 | G8: =D8*F8 -> 0
A10: Total lever impact (item-level view) | G10: =SUM(G5:G8) -> 25.506741
A11: Base-case landing (Model) | G11: =Model!K19 -> 5016.8563
A12: Landing if item levers deliver | G12: =G11+G10 -> 5042.363
A13: Cushion vs PHP 5B | G13: =G12-Model!B3 -> 42.362998
A16: 1 PROTECT: top items by remaining revenue (stable or growing)
A17: Rank | B17: Item | C17: Channel / category | D17: Projected remainder (PHP M) | E17: Growth % (Jan+Jul) | F17: Change (PHP M, 2 months)
A18: 1 | B18: SIRLOIN BEEF TAPA - PLATE (ADB-SBT1) | C18: Cafe / ALL-DAY BREAKFAST | D18: 69.506494 | E18: 0.095026366 | F18: 3.6202441
A19: 2 | B19: MARY GRACE CHEESEROLLS - BOX OF 12 (CRC-MGCR12) | C19: Cafe / CHEESE ROLLS | D19: 42.717265 | E19: 0.045249934 | F19: 1.2252027
A20: 3 | B20: DAING NA BANGUS - PLATE (ADB-FBB1) | C20: Cafe / ALL-DAY BREAKFAST | D20: 33.711471 | E20: 0.12387888 | F20: 2.2960709
A21: 4 | B21: MARY GRACE MUSHROOM CREAM - PLATE (FPCR-MGMC1) | C21: Cafe / FLAVORFUL PASTAS | D21: 23.312348 | E21: -0.0098198504 | F21: -0.10509471
A22: 5 | B22: TOASTED VIGAN LONGGANISA - PLATE (ADB-TVL1) | C22: Cafe / ALL-DAY BREAKFAST | D22: 22.856725 | E22: 0.43365231 | F22: 3.1930149
A23: 6 | B23: SPICY LEMON SCAMPI - PLATE (FPOL-SLS1) | C23: Cafe / FLAVORFUL PASTAS | D23: 22.779571 | E23: 0.1250883 | F23: 1.0983317
A24: 7 | B24: MARY GRACE CHEESEROLLS - BOX OF 6 (CRC-MGCR6) | C24: Cafe / CHEESE ROLLS | D24: 22.220563 | E24: 0.062581155 | F24: 0.85711371
A25: 8 | B25: SEAFOOD PASTA - PLATE (FPOL-SP1) | C25: Cafe / FLAVORFUL PASTAS | D25: 22.070978 | E25: -0.0020024871 | F25: -0.020032223
A26: 9 | B26: MARY GRACE HOT CHOCOLATE CUP (BEVHC-MGHC1) | C26: Cafe / BEVERAGES | D26: 21.530115 | E26: 0.074699847 | F26: 1.0170074
A27: 10 | B27: PERFECT PLATE - FRESH TOMATO & HERB (PPP-FTHP1) | C27: Cafe / PERFECT PLATES | D27: 20.108555 | E27: 0.01645402 | F27: 0.26199961
A28: 11 | B28: MARY GRACE ENSAYMADA - BOX OF 6 (EQC-MGE6) | C28: Cafe / ENSAYMADAS | D28: 19.295204 | E28: 0.0054710846 | F28: 0.075295982
A29: 12 | B29: AMERICANO HOT CUP (BEVCF-AMEH1) | C29: Cafe / BEVERAGES | D29: 15.02818 | E29: 0.1314561 | F29: 1.1955129
... A42: 25 | B42: PRAWN SALAD WITH PAPAYA - PLATE (FS-PSMPV1) | C42: Cafe / FRESH SALADS | D42: 9.2531105 | E42: 0.0055525146 | F42: 0.035056911
A45: 2 FIX: top-80% items that are shrinking (biggest first)
A46: Rank | B46: Item | C46: Channel / category | D46: Projected remainder (PHP M) | E46: Growth % (Jan+Jul) | F46: Change (PHP M, 2 months)
A47: 1 | B47: RIB-EYE SALPICAO AND EGGS - PLATE (ADB-SALPI1) | C47: Cafe / ALL-DAY BREAKFAST | D47: 35.174687 | E47: -0.052765556 | F47: -1.216396
A48: 2 | B48: MARY GRACE CHEESEROLLS - PC (CRC-MGCR1) | C48: Kiosk & Others / CHEESE ROLLS | D48: 27.918575 | E48: -0.099168876 | F48: -0.23088214
A49: 3 | B49: MANGO BENE SLICE (SCS-MB1) | C49: Cafe / SIGNATURE CAKES | D49: 15.336468 | E49: -0.079398491 | F49: -0.78928948
A50: 4 | B50: MARY GRACE ENSAYMADA - PC (EQC-MGE1) | C50: Kiosk & Others / ENSAYMADA | D50: 12.611413 | E50: -0.14283579 | F50: -0.34720179
A51: 5 | B51: TOASTED ALMOND SANS RIVAL WHOLE (SCW-TASR1) | C51: Kiosk & Others / SANSRIVAL | D51: 7.3612158 | E51: -0.098694312 | F51: -0.2669875
A52: 6 | B52: MANGO BENE MINI - PC (SCM-MB1) | C52: Cafe / SIGNATURE CAKES | D52: 7.2545745 | E52: -0.065149148 | F52: -0.28747124
A53: 7 | B53: CHOCOLATE RUM TIRAMISU SLICE - PC (SEAS-CTI1) | C53: Cafe / SIGNATURE CAKES | D53: 6.6122256 | E53: -0.1014053 | F53: -0.47704795
A54: 8 | B54: MARY GRACE ENSAYMADA - PC (EQC-MGE1) | C54: Cafe / ENSAYMADAS | D54: 5.9526631 | E54: -0.085947829 | F54: -0.41569684
A55: 9 | B55: STRAWBERRY SHORTCAKE WHOLE (SCW-SS1) | C55: Kiosk & Others / SIGNATURE CAKES | D55: 5.8748823 | E55: -0.18517951 | F55: -0.017251786
A56: 10 | B56: CHOCOLATE TRUFFLE WHOLE (SCW-CT1) | C56: Kiosk & Others / TRUFFLE | D56: 5.3895465 | E56: -0.074056004 | F56: -0.30154618
A57: 11 | B57: MARY GRACE CHEESEROLLS - PC (CRC-MGCR1) | C57: Cafe / CHEESE ROLLS | D57: 5.3348818 | E57: -0.061273227 | F57: -0.23513434
A58: 12 | B58: RIB-EYE SALPICAO AND EGGS - SHARE (ADBSH-SALPI1) | C58: Cafe / ALL-DAY BREAKFAST | D58: 4.9713936 | E58: -0.065810372 | F58: -0.20414107
... A61: 15 | B61: CHEDDAR CHEESE TOMATO CAPERS - PLATE (SS-CCTC1) | C61: Cafe / SAVORY STARTERS | D61: 3.9359314 | E61: -0.068103663 | F61: -0.21152078
A64: 3 SCALE: growing or new items outside the top 80% (biggest recent revenue first)
A65: Rank | B65: Item | C65: Channel / category | D65: Projected remainder (PHP M) | E65: Growth % (Jan+Jul) | F65: Change (PHP M, 2 months)
A66: 1 | B66: FILI BEEF SET (HSSE-FBT1) | C66: Cafe / HEARTY SANDWICHES | D66: 2.5405084 | E66: 10.064585 | F66: 1.6780089
A67: 2 | B67: VIGAN LONGGANISA AND KESONG PUTI (HSSO-VLKP1) | C67: Cafe / HEARTY SANDWICHES | D67: 2.3875993 | E67: 15.108698 | F67: 1.583567
A68: 3 | B68: SUMMER SALAD WITH STRAWBERRY - SHARE (FSSH-SUMMER1) | C68: Cafe / FRESH SALADS | D68: 2.2267106 | E68: 0.31285121 | F68: 0.36993986
A69: 4 | B69: CARROT CAKE MINI (SCM-CWC1) | C69: Kiosk & Others / GRABFOOD | D69: 1.8371246 | E69: new | F69: 1.4839786
A70: 5 | B70: ITALIAN MEATBALL WHOLE (PZNE-IM13) | C70: Cafe / PIZZAS | D70: 2.3816591 | E70: 0.4696311 | F70: 0.46270446
A71: 6 | B71: MARGHERITA WHOLE (PZNE-MARG13) | C71: Cafe / PIZZAS | D71: 2.432972 | E71: 0.46026739 | F71: 0.44345982
A72: 7 | B72: CHICKEN INASAL SET (HSSE-CI1) | C72: Cafe / HEARTY SANDWICHES | D72: 1.8629309 | E72: 10.340754 | F72: 1.2122318
A73: 8 | B73: PARMESAN CHICKEN TENDERS (KM-PCT1) | C73: Cafe / KIDS MENU | D73: 2.6231597 | E73: 1.2780278 | F73: 0.74439643
A74: 9 | B74: AFFOGATO SLICE - PC (SEAS-AFFO1) | C74: Cafe / SEASONAL CAKES | D74: 1.5260829 | E74: new | F74: 1.2995515
A75: 10 | B75: VIGAN LONGGANISA AND KESONG PUTI SET (HSSE-VLKP1) | C75: Cafe / HEARTY SANDWICHES | D75: 1.6388639 | E75: 9.2735214 | F75: 1.1620964
A76: 11 | B76: GARLIC SHRIMP (HSSO-PSS1) | C76: Cafe / HEARTY SANDWICHES | D76: 1.7155911 | E76: 14.825922 | F76: 1.1658072
A77: 12 | B77: TSOKNUT LENGUA (PAL-CL1) | C77: Cafe / PASTRIES | D77: 2.0835755 | E77: new | F77: 1.2348789
A78: 13 | B78: DOUBLE CHOCOLATE BROWNIES - BOX OF 8 (DB-DCHOCO8) | C78: Cafe / DESSERT BARS | D78: 2.4427516 | E78: new | F78: 1.2066562
A79: 14 | B79: BISCOFF CRUNCH BROWNIES - BOX OF 8 (DB-BISCOF8) | C79: Cafe / DESSERT BARS | D79: 2.0599283 | E79: new | F79: 1.1924286
A80: 15 | B80: BANANA SHAKE GLASS (BEVFFS-B1) | C80: Cafe / BEVERAGES | D80: 1.7822437 | E80: 0.25421847 | F80: 0.22294407

Sheet Levers_Scenarios
A1: What it takes to land the PHP 5B: sensitivities and lever sizing (PHP millions)
A3: 1) Landing vs target at different Oct 20-Dec 31 growth rates (vs the same days of 2025)
A4: Remainder YoY growth | B4: FY2026 landing | C4: Vs PHP 5B target | D4: Hit target?
A5: -0.05 | B5: =Model!$E$19+Model!$F$19*(1+A5) -> 4923.5674 | C5: =B5-Model!$B$3 -> -76.432554 | D5: =IF(C5>=0,"Yes","No") -> No
A6: -0.03 | B6: =Model!$E$19+Model!$F$19*(1+A6) -> 4945.9584 | C6: =B6-Model!$B$3 -> -54.041605 | D6: =IF(C6>=0,"Yes","No") -> No
A7: -0.01 | B7: =Model!$E$19+Model!$F$19*(1+A7) -> 4968.3493 | C7: =B7-Model!$B$3 -> -31.650657 | D7: =IF(C7>=0,"Yes","No") -> No
A8: 0 | B8: =Model!$E$19+Model!$F$19*(1+A8) -> 4979.5448 | C8: =B8-Model!$B$3 -> -20.455183 | D8: =IF(C8>=0,"Yes","No") -> No
A9: 0.018 | B9: =Model!$E$19+Model!$F$19*(1+A9) -> 4999.6967 | C9: =B9-Model!$B$3 -> -0.30332882 | D9: =IF(C9>=0,"Yes","No") -> No
A10: 0.033 | B10: =Model!$E$19+Model!$F$19*(1+A10) -> 5016.4899 | C10: =B10-Model!$B$3 -> 16.489883 | D10: =IF(C10>=0,"Yes","No") -> Yes
A11: 0.05 | B11: =Model!$E$19+Model!$F$19*(1+A11) -> 5035.5222 | C11: =B11-Model!$B$3 -> 35.522189 | D11: =IF(C11>=0,"Yes","No") -> Yes
A12: 0.07 | B12: =Model!$E$19+Model!$F$19*(1+A12) -> 5057.9131 | C12: =B12-Model!$B$3 -> 57.913137 | D12: =IF(C12>=0,"Yes","No") -> Yes
A14: Break-even growth in the remainder | B14: =Model!B28 -> 0.018270939
A15: Projected growth in the remainder (base case) | B15: =Model!B29 -> 0.033327252
A17: 2) December dependence
A18: Dec 2025 total net sales | B18: =Monthly_Data!N13 -> 573.96429
A19: Dec 2026 implied by base case | B19: =B18*Model!J19/Model!F19 -> 593.09294
A20: Share of the Oct 20-Dec 31 projection that is December | B20: =B19/Model!J19 -> 0.51267528
A21: Cushion vs target as % of projected December | B21: =Model!B24/B19 -> 0.028420937
A22: Each 1% on December is worth (PHP M) | B22: =B19*0.01 -> 5.9309294
A24: 3) Lever sizing (illustrative: base x assumed uplift; blue cells are assumptions you can change)
A25: Lever | B25: Base it applies to (PHP M) | C25: Assumed uplift | D25: Impact (PHP M) | E25: Evidence from the data / how to execute
A26: Cafe same-store traffic +1.0 pt (all categories) in Oct 20-Dec 31 | B26: =Model!J11 -> 916.63517 | C26: 0.01 | D26: =B26*C26 -> 9.1663517 | E26: Same-store volume is shrinking in most big categories (Beverages qty -5%, Perfect Plates -7%, Ensaymadas -7%); growth is price-led. Loyalty / bundle / meal-deal offers aimed at visits, not price.
A27: December cakes & celebration push (Signature + Loaf Cakes) +3% | B27: =(84.2594+10.5804)*Model!$J$11/Model!$F$11 -> 96.831155 | C27: 0.03 | D27: =B27*C27 -> 2.9049347 | E27: Signature Cakes jump from ~PHP 56M in Nov to ~PHP 84M in Dec 2025 (cafe same-stores). Secure cake pre-orders, production capacity and stock for 2026 peak.
A28: Kiosk December / Christmas programme +5% | B28: =Monthly_Data!N9*Model!$J$15/Model!$F$15 -> 74.912613 | C28: 0.05 | D28: =B28*C28 -> 3.7456306 | E28: Kiosk Same-Store doubles in Dec 2025 (~PHP 37M Nov to ~PHP 74M Dec). Christmas, Fruitcake, Mango Bene and Cheese Rolls lead the uplift.
A29: Stop the decline in Perfect Plates, Ensaymadas, Loaf Cakes (back to flat) | B29: =99.0373*Model!$J$11/Model!$F$11 -> 101.11679 | C29: 0.07 | D29: =B29*C29 -> 7.0781753 | E29: YTD same-store: Perfect Plates -8.1%, Ensaymadas -5.6%, Loaf Cakes -10.7%. Uplift = blended decline rate; review pricing, availability, promo and menu placement.
A30: New cafes opened 2026: Sep run-rate holds vs Q3 average | B30: =(Monthly_Data!W7-AVERAGE(Monthly_Data!U7:W7))*Model!I13 -> 4.1841091 | C30: 1 | D30: =B30*C30 -> 4.1841091 | E30: Cohort sales stepped up to ~PHP 5.8M in Sep from ~PHP 3.8M in Jul. Base model uses the Q3 average, so holding Sep adds the difference. Needs store counts to refine.
A31: Kiosk delivery (GrabFood) stops declining | B31: =17.4492 -> 17.4492 | C31: 0.126 | D31: =B31*C31 -> 2.1985992 | E31: GrabFood is the biggest kiosk drag YTD (-12.6%, about -PHP 7.5M). Check delivery fees, promos and availability on the platform.
A32: Total of levers (not a forecast: levers overlap and need execution) | D32: =SUM(D26:D31) -> 29.277801
A33: Base-case landing | D33: =Model!K19 -> 5016.8563
A34: Landing if levers deliver in full | D34: =D33+D32 -> 5046.1341
A35: Cushion vs target with levers | D35: =D34-Model!B3 -> 46.134058
A36: Cushion as % of target | D36: =D35/Model!B3 -> 0.0092268115

Sheet Notes_Recon
A1: Reconciliation and data notes
A3: Extract | B3: Receipts | C3: Header net (PHP M) | D3: Line-level net allocated (PHP M) | E3: Line / header | F3: Scale factor used | G3: Note
A4: Jan_July_2025 | B4: 1881865 | C4: 2329.8157 | D4: 2212.5155 | E4: =D4/C4 -> 0.94965256 | F4: =C4/D4 -> 1.0530167 | G4: Raw export ties at ~95% of header (lines exclude voids/other header items)
A5: July2025_Jan2026 | B5: 1989918 | C5: 2500.7145 | D5: 2378.3593 | E5: =D5/C5 -> 0.9510719 | F5: =C5/D5 -> 1.0514452 | G5: Raw export ties at ~95% of header (lines exclude voids/other header items)
A6: Jan_July_2026 | B6: 1931837 | C6: 2424.9814 | D6: 2297.7559 | E6: =D6/C6 -> 0.94753546 | F6: =C6/D6 -> 1.0553695 | G6: Includes ~PHP 45M of estimated rows (export hit the 1,000-row limit); raw export was only 92.9% of header
A7: July2026_Present | B7: 1130406 | C7: 1435.016 | D7: 1363.2009 | E7: =D7/C7 -> 0.94995523 | F7: =C7/D7 -> 1.0526812 | G7: Raw export ties at ~95% of header (lines exclude voids/other header items)
A9: DATA ISSUES TO CLOSE
A10: 1. The Jan-Jun 2026 export stopped at exactly 1,000 rows. It dropped the tail of Kiosk Same-Store (Sansrival to Truffle) and all "Others" rows. I rebuilt them from the complete January 2026 tab, scaled by month. Re-run that period with the row limit removed (or in two 3-month runs) to replace the estimates. The total is unaffected because every extract is scaled to receipt-level net.
A11: 2. Line-level net is ~95% of receipt-level net in every complete extract. Each extract is scaled to its header_net so totals match what POSHQ / the STRAT SHEET should show. Jan 2025 ties exactly to your Step 3 result (PHP 402.3M). The mix across categories assumes the 5% gap is spread evenly.
A12: 3. The tab named "2026" is a duplicate January 2026 run; it was used only to patch the truncated rows, not added to totals.
A13: 4. 2026 data runs to Oct 19. Oct 2025 is pro-rated 19/31 and the Oct 20-31 base is 12/31 of Oct 2025 (even daily pace assumed).
A14: 5. "Closing" stores = branches with a date_closed recorded; they still trade for part of the period. Same-Store = date_opened before 2025-01-01 and no close date. "Others" (one branch) is folded into Kiosk.
A15: 6. Seasonality comes from 2025 only. December 2025 was PHP 574M vs PHP 397M in November. If 2024 shows a smaller December step-up, the landing is lower than shown.
A16: 7. Net sales here are VAT-inclusive and net of discounts (receipt net_amount), matching the stated basis of the target.
A17: 8. ITEM EXPORTS ARE INCOMPLETE: each of the four item files holds only its first 1,000 rows (the rest is "undefined" filler from the export). Only Jan 2025, Jul 2025, Jan 2026 and Jul 2026 are complete; they match the category extracts to the peso. Pareto_Items and Item_Priorities use those months. Run pull_item_data.py to get every month and replace the provisional results.
A18: 9. Item remainder = the category projected remainder (Pareto_Categories) shared across its items by July-2026 revenue. Items that sell mainly in December are under-stated until item-level Q4 2025 data is available. About PHP 26M of kiosk seasonal categories with no July sales is left unallocated.
A19: 10. Item revenue for ranking = unit price / 1.12 x qty (ex-VAT, team definition). Peso projections stay on the VAT-inclusive net basis of the target. Items missing an item_id in the master (about 0.07% of sales) are combined into one "(unmapped)" line.
